{
 "updated": "2026-07-21",
 "source": "https://nsearchives.nseindia.com/content/equities/sec_list.csv",
 "count": 3308,
 "changesApplied": 5,
 "bands": {
  "21STCENMGM": 2,
  "AAREYDRUGS": 2,
  "ACCORD": 2,
  "AKSHOPTFBR": 2,
  "AMANTA": 2,
  "ANSALAPI": 2,
  "APSISAERO": 2,
  "ASCOM": 2,
  "ATCENERGY": 2,
  "AVATAR": 2,
  "BAFNAPH": 2,
  "BLUECHIP": 2,
  "DCMSIL": 2,
  "DIVYADHAN": 2,
  "FEL": 2,
  "GLFL": 2,
  "GRCL": 2,
  "GTECJAINX": 2,
  "GVKPIL": 2,
  "INNOMET": 2,
  "ITTL": 2,
  "KESORAMIND": 2,
  "LOKESHMACH": 2,
  "MEP": 2,
  "NAMOEWASTE": 2,
  "NEWJAISA": 2,
  "NRL": 2,
  "PALREDTEC": 2,
  "PARSVNATH": 2,
  "PENINLAND": 2,
  "PRIZOR": 2,
  "RADIOWALLA": 2,
  "RAJRILTD": 2,
  "RSSOFTWARE": 2,
  "SADHNANIQ": 2,
  "SAHASRA": 2,
  "SANGINITA": 2,
  "SANWARIA": 2,
  "SETCO": 2,
  "SEYAIND": 2,
  "SHIVAMAUTO": 2,
  "SHYAMTEL": 2,
  "SIGACHI": 2,
  "SITINET": 2,
  "SUPERSPIN": 2,
  "SUPREMEENG": 2,
  "SVLL": 2,
  "SWASTIK": 2,
  "TANKUP": 2,
  "UCL": 2,
  "UHTL": 2,
  "VIJIFIN": 2,
  "VITAL": 2,
  "VLEGOV": 2,
  "VPRPL": 2,
  "WINSOME": 2,
  "ZIMLAB": 2,
  "AAKAAR": 5,
  "AARTECH": 5,
  "ABAN": 5,
  "ABANSENT": 5,
  "ABSLLIQUID": 5,
  "ABSMARINE": 5,
  "ACCPL": 5,
  "ACCURACY": 5,
  "ACSTECH": 5,
  "ADDICTIVE": 5,
  "AEROPLANE": 5,
  "AFFORDABLE": 5,
  "AGARWALFT": 5,
  "AGNI": 5,
  "AGRITECH": 5,
  "AGUL": 5,
  "AHIMSA": 5,
  "AHLWEST": 5,
  "AILIMITED": 5,
  "AISL": 5,
  "AKANKSHA": 5,
  "AKIKO": 5,
  "AKSHARCHEM": 5,
  "ALCODIS": 5,
  "ALKALI": 5,
  "ALLETEC": 5,
  "ALPINETEX": 5,
  "AMBANIORGO": 5,
  "AMEYA": 5,
  "ANIKINDS": 5,
  "ANKITMETAL": 5,
  "ANLON": 5,
  "ANTELOPUS": 5,
  "AONELIQUID": 5,
  "APEXECO": 5,
  "APTECHT": 5,
  "AQYLON": 5,
  "ARCIIL": 5,
  "ARISTO": 5,
  "ARMOUR": 5,
  "ARROWGREEN": 5,
  "ARSHIYA": 5,
  "ARUNAYA": 5,
  "ARVINDPORT": 5,
  "ASMS": 5,
  "ASPIRE": 5,
  "ASTRON": 5,
  "ATLANTAELE": 5,
  "ATMASTCO": 5,
  "AUROIMPEX": 5,
  "AUSL": 5,
  "AUSOMENT": 5,
  "AUTOIND": 5,
  "AVADHSUGAR": 5,
  "AVANA": 5,
  "AVG": 5,
  "AVPINFRA": 5,
  "AVSL": 5,
  "AXISCADES": 5,
  "BALAXI": 5,
  "BALCO": 5,
  "BANKA": 5,
  "BASML": 5,
  "BAWEJA": 5,
  "BDR": 5,
  "BEACON": 5,
  "BEDMUTHA": 5,
  "BGRENERGY": 5,
  "BHADORA": 5,
  "BHAGERIA": 5,
  "BHAGYANGR": 5,
  "BHANDARI": 5,
  "BHARATGEAR": 5,
  "BIKEWO": 5,
  "BILVYAPAR": 5,
  "BIRDYS": 5,
  "BIRLACABLE": 5,
  "BLACKROSE": 5,
  "BLISSGVS": 5,
  "BLUECOAST": 5,
  "BLUEWATER": 5,
  "BNAGROCHEM": 5,
  "BNALTD": 5,
  "BODALCHEM": 5,
  "BOHRAIND": 5,
  "BONLON": 5,
  "BOSS": 5,
  "BRANDMAN": 5,
  "BROOKS": 5,
  "BSHSL": 5,
  "BTTL": 5,
  "BULKCORP": 5,
  "BYKE": 5,
  "CADSYS": 5,
  "CALSOFT": 5,
  "CAPTRUST": 5,
  "CASHIETF": 5,
  "CBAZAAR": 5,
  "CEDAAR": 5,
  "CELLECOR": 5,
  "CEMPRO": 5,
  "CEREBRAINT": 5,
  "CHEMBOND": 5,
  "CHEMBONDCH": 5,
  "CHEMCON": 5,
  "CHEMFAB": 5,
  "CHETANA": 5,
  "CLASSICEIL": 5,
  "CLEDUCATE": 5,
  "CMRSL": 5,
  "COFFEEDAY": 5,
  "COMMITTED": 5,
  "COMPINFO": 5,
  "CONTI": 5,
  "COOLCAPS": 5,
  "CORDSCABLE": 5,
  "CPCAP": 5,
  "CPPLUS": 5,
  "CPS": 5,
  "CRAYONS": 5,
  "CUDML": 5,
  "CYBERMEDIA": 5,
  "CYBERTECH": 5,
  "DAICHI": 5,
  "DAMODARIND": 5,
  "DANGEE": 5,
  "DBEIL": 5,
  "DBREALTY": 5,
  "DBSTOCKBRO": 5,
  "DCM": 5,
  "DCMFINSERV": 5,
  "DCMNVL": 5,
  "DEEDEV": 5,
  "DEEM": 5,
  "DELPHIFX": 5,
  "DELTIC": 5,
  "DESTINY": 5,
  "DHANSA": 5,
  "DHARAN": 5,
  "DHARARAIL": 5,
  "DHRUV": 5,
  "DHTL": 5,
  "DIGISPICE": 5,
  "DIRL": 5,
  "DISHTV": 5,
  "DIVINEHIRA": 5,
  "DPEL": 5,
  "DPSCLTD": 5,
  "DPWIRES": 5,
  "DRONE": 5,
  "DRSCARGO": 5,
  "DRSDILIP": 5,
  "DSFCL": 5,
  "DSSL": 5,
  "DUGLOBAL": 5,
  "DURLAX": 5,
  "DYNAMIC": 5,
  "E2E": 5,
  "E2ERAIL": 5,
  "EASTSILK": 5,
  "EBGNG": 5,
  "ECOLINE": 5,
  "ECOSMOBLTY": 5,
  "EFFWA": 5,
  "EIFFL": 5,
  "ELIQUID": 5,
  "EMAMIREAL": 5,
  "EMMBI": 5,
  "EMPOWER": 5,
  "EPWINDIA": 5,
  "EQUIPPP": 5,
  "ESFL": 5,
  "ESSENTIA": 5,
  "EUROTEXIND": 5,
  "EVERESTIND": 5,
  "EXCELLENT": 5,
  "FAIRCHEMOR": 5,
  "FAZE3Q": 5,
  "FCSSOFT": 5,
  "FELDVR": 5,
  "FIBERWEB": 5,
  "FILATFASH": 5,
  "FLEXITUFF": 5,
  "FLFL": 5,
  "FMNL": 5,
  "FOCE": 5,
  "FOCUS": 5,
  "FONEBOX": 5,
  "FORGEAUTO": 5,
  "FROG": 5,
  "GALLANTT": 5,
  "GANESHIN": 5,
  "GANGAFORGE": 5,
  "GAUDIUMIVF": 5,
  "GAYAPROJ": 5,
  "GCHOTELS": 5,
  "GEECEE": 5,
  "GICL": 5,
  "GILT10BETA": 5,
  "GILT5BETA": 5,
  "GILT5YBEES": 5,
  "GINNIFILA": 5,
  "GIRIRAJ": 5,
  "GJL": 5,
  "GLOBALE": 5,
  "GLOBALPET": 5,
  "GLOBECIVIL": 5,
  "GLOTTIS": 5,
  "GML": 5,
  "GOLDENTOBC": 5,
  "GOLDKART": 5,
  "GOLDSTAR": 5,
  "GOLDTECH": 5,
  "GPECO": 5,
  "GRADIENTE": 5,
  "GRANDOAK": 5,
  "GRAPHISAD": 5,
  "GREENCHEF": 5,
  "GREENLEAF": 5,
  "GRETEX": 5,
  "GROWWLIQID": 5,
  "GSEC10IETF": 5,
  "GSEC10YEAR": 5,
  "GSEC5IETF": 5,
  "GSLSU": 5,
  "GSTL": 5,
  "GUJRAFFIA": 5,
  "GULFPETRO": 5,
  "GURUNANAK": 5,
  "GVPIL": 5,
  "HALDYNGL": 5,
  "HAPPY": 5,
  "HBSL": 5,
  "HDFCLIQUID": 5,
  "HDIL": 5,
  "HEXAGON": 5,
  "HFCL": 5,
  "HILINFRA": 5,
  "HILTON": 5,
  "HINDCON": 5,
  "HITECHCORP": 5,
  "HITECHGEAR": 5,
  "HMT": 5,
  "HOACFOODS": 5,
  "HOLMARC": 5,
  "HOMESFY": 5,
  "HPTL": 5,
  "HRHNEXT": 5,
  "HVAX": 5,
  "HYBRIDFIN": 5,
  "IBLFL": 5,
  "IBULLSLTD": 5,
  "ICELCO": 5,
  "IDEAFORGE": 5,
  "IEML": 5,
  "IFBAGRO": 5,
  "IL&FSENGG": 5,
  "IL&FSTRANS": 5,
  "INDIFRA": 5,
  "INDOAMIN": 5,
  "INDOTECH": 5,
  "INDOWIND": 5,
  "INFINIUM": 5,
  "INSPIRE": 5,
  "INSPIRISYS": 5,
  "INTEGRITY": 5,
  "INVICTA": 5,
  "ISHAN": 5,
  "IVP": 5,
  "IWARE": 5,
  "IZMO": 5,
  "JAIBALAJI": 5,
  "JAINAM": 5,
  "JAINIK": 5,
  "JAKHARIA": 5,
  "JALAN": 5,
  "JAYBARMARU": 5,
  "JETKNIT": 5,
  "JEYYAM": 5,
  "JFLLIFE": 5,
  "JINDALPOLY": 5,
  "JITFINFRA": 5,
  "JKIPL": 5,
  "JOCIL": 5,
  "K2INFRA": 5,
  "KAKATCEM": 5,
  "KALYANI": 5,
  "KAMDHENU": 5,
  "KANCHI": 5,
  "KANORICHEM": 5,
  "KAUSHALYA": 5,
  "KCEIL": 5,
  "KDL": 5,
  "KECL": 5,
  "KHADIM": 5,
  "KHAICHEM": 5,
  "KHAITANLTD": 5,
  "KILITCH": 5,
  "KKVAPOW": 5,
  "KONSTELEC": 5,
  "KOPRAN": 5,
  "KOTYARK": 5,
  "KRIDHANINF": 5,
  "KRITI": 5,
  "KRITINUT": 5,
  "KRMAYURVED": 5,
  "KRN": 5,
  "KSHITIJPOL": 5,
  "KSR": 5,
  "LAKPRE": 5,
  "LAKSHYA": 5,
  "LAMOSAIC": 5,
  "LATTEYS": 5,
  "LAXMIINDIA": 5,
  "LCCINFOTEC": 5,
  "LEMERITE": 5,
  "LICNETFGSC": 5,
  "LIQGRWBEES": 5,
  "LIQUID": 5,
  "LIQUID1": 5,
  "LIQUIDADD": 5,
  "LIQUIDBEES": 5,
  "LIQUIDBETA": 5,
  "LIQUIDBETF": 5,
  "LIQUIDCASE": 5,
  "LIQUIDETF": 5,
  "LIQUIDIETF": 5,
  "LIQUIDPLUS": 5,
  "LIQUIDSBI": 5,
  "LIQUIDSHRI": 5,
  "LLOYDS": 5,
  "LTGILTBEES": 5,
  "LTGILTCASE": 5,
  "LYKALABS": 5,
  "MADHAVBAUG": 5,
  "MADHUCON": 5,
  "MADHUSUDAN": 5,
  "MAHESHWARI": 5,
  "MAKS": 5,
  "MAL": 5,
  "MANAKSTEEL": 5,
  "MANAV": 5,
  "MANDEEP": 5,
  "MANGALAM": 5,
  "MANORG": 5,
  "MANUGRAPH": 5,
  "MARALOVER": 5,
  "MARINETRAN": 5,
  "MASKINVEST": 5,
  "MASTER": 5,
  "MAWANASUG": 5,
  "MAXVOLT": 5,
  "MAZDA": 5,
  "MBLINFRA": 5,
  "MCLEODRUSS": 5,
  "MCON": 5,
  "MDL": 5,
  "MEDIORG": 5,
  "MEGAFLEX": 5,
  "MEIL": 5,
  "MENONBE": 5,
  "MERCURYEV": 5,
  "MGEL": 5,
  "MHHL": 5,
  "MHLXMIRU": 5,
  "MICEL": 5,
  "MIEL": 5,
  "MILTON": 5,
  "MINDPOOL": 5,
  "MITCON": 5,
  "MMEL": 5,
  "MMWL": 5,
  "MOBILISE": 5,
  "MODINATUR": 5,
  "MODISONLTD": 5,
  "MOGSEC": 5,
  "MONOPHARMA": 5,
  "MOS": 5,
  "MOTOGENFIN": 5,
  "MOXSH": 5,
  "MPEL": 5,
  "MPTODAY": 5,
  "MRIL": 5,
  "MSPL": 5,
  "MTARTECH": 5,
  "MTEDUCARE": 5,
  "MUKTAARTS": 5,
  "MUNISH": 5,
  "NAGREEKCAP": 5,
  "NAHARSPING": 5,
  "NAMAN": 5,
  "NATIONSTD": 5,
  "NAVKARURB": 5,
  "NEAGI": 5,
  "NECCLTD": 5,
  "NECLIFE": 5,
  "NEELAM": 5,
  "NEOCHEM": 5,
  "NEPHROCARE": 5,
  "NEUEON": 5,
  "NFPSAMPOOR": 5,
  "NGIL": 5,
  "NIKITA": 5,
  "NIMBSPROJ": 5,
  "NINSYS": 5,
  "NIRAJ": 5,
  "NOIDATOLL": 5,
  "NORBTEAEXP": 5,
  "NOVAAGRI": 5,
  "NRVANDANA": 5,
  "OCCLLTD": 5,
  "ODIGMA": 5,
  "OILCOUNTUB": 5,
  "OLIL": 5,
  "OMAXAUTO": 5,
  "OMFREIGHT": 5,
  "OMFURN": 5,
  "ONELIFECAP": 5,
  "ONIDA": 5,
  "ONMOBILE": 5,
  "ONYX": 5,
  "ORBTEXP": 5,
  "ORTEL": 5,
  "ORTINGLOBE": 5,
  "OSIAHYPER": 5,
  "OSWALAGRO": 5,
  "OWAIS": 5,
  "PANACHE": 5,
  "PARAMOUNT": 5,
  "PARAMPARA": 5,
  "PASUPTAC": 5,
  "PATILAUTOM": 5,
  "PATINTLOG": 5,
  "PATTECH": 5,
  "PEARLPOLY": 5,
  "PERFECT": 5,
  "PILITA": 5,
  "PLADAINFO": 5,
  "PLAZACABLE": 5,
  "POSITRON": 5,
  "POWERICA": 5,
  "PPAP": 5,
  "PPL": 5,
  "PPSL": 5,
  "PRADPME": 5,
  "PRAMARA": 5,
  "PRAXIS": 5,
  "PRECISION": 5,
  "PRECOT": 5,
  "PREMIER": 5,
  "PRIMECAB": 5,
  "PRITI": 5,
  "PRITIKAUTO": 5,
  "PROLIFE": 5,
  "PRUDMOULI": 5,
  "PSRAJ": 5,
  "PULZ": 5,
  "PURPLEUTED": 5,
  "PURVFLEXI": 5,
  "QFIL": 5,
  "QPOWER": 5,
  "QUADPRO": 5,
  "QUICKHEAL": 5,
  "QUICKTOUCH": 5,
  "QVCEL": 5,
  "RAJESHEXPO": 5,
  "RAJOOENG": 5,
  "RAJTV": 5,
  "RAMASTEEL": 5,
  "RBS": 5,
  "RCOM": 5,
  "REFRACTORY": 5,
  "REGAAL": 5,
  "REPL": 5,
  "REXPIPES": 5,
  "REXPRO": 5,
  "RFBL": 5,
  "RHFL": 5,
  "RICHA": 5,
  "RITEZONE": 5,
  "RMDRIP": 5,
  "RNBDENIMS": 5,
  "RNPL": 5,
  "ROLLT": 5,
  "ROXHITECH": 5,
  "RPSGVENT": 5,
  "RSWM": 5,
  "RUBYMILLS": 5,
  "RUDRA": 5,
  "S&SPOWER": 5,
  "SAAKSHI": 5,
  "SABAR": 5,
  "SABEVENTS": 5,
  "SADBHIN": 5,
  "SAIFL": 5,
  "SAJHOTELS": 5,
  "SAKUMA": 5,
  "SALSTEEL": 5,
  "SAMAY": 5,
  "SANGANI": 5,
  "SAROJA": 5,
  "SARVESHWAR": 5,
  "SASKEN": 5,
  "SATECH": 5,
  "SATIPOLY": 5,
  "SATKARTAR": 5,
  "SAYAJIHOTL": 5,
  "SBILIQETF": 5,
  "SEJALLTD": 5,
  "SEMAC": 5,
  "SERVICE": 5,
  "SETF10GILT": 5,
  "SETL": 5,
  "SETUINFRA": 5,
  "SHAIVAL": 5,
  "SHARDUL": 5,
  "SHEEL": 5,
  "SHEKHAWATI": 5,
  "SHEMAROO": 5,
  "SHERA": 5,
  "SHETHJI": 5,
  "SHIVALIK": 5,
  "SHIVAMILLS": 5,
  "SHRENIK": 5,
  "SHRIAHIMSA": 5,
  "SHRIKANHA": 5,
  "SHUBHLAXMI": 5,
  "SHYAMCENT": 5,
  "SHYAMDHANI": 5,
  "SICALLOG": 5,
  "SIDDHIKA": 5,
  "SIGMAADV": 5,
  "SIGNORIA": 5,
  "SILKFLEX": 5,
  "SILVERTUC": 5,
  "SIMBHALS": 5,
  "SLONE": 5,
  "SMARTEN": 5,
  "SMARTLINK": 5,
  "SMVD": 5,
  "SNEHAA": 5,
  "SOCL": 5,
  "SOFTTECH": 5,
  "SOMATEX": 5,
  "SONAL": 5,
  "SONUINFRA": 5,
  "SOTAC": 5,
  "SPCENET": 5,
  "SPEB": 5,
  "SPECTSTM": 5,
  "SPPPOLY": 5,
  "SPRL": 5,
  "SRIVASAVI": 5,
  "SSFL": 5,
  "STERTOOLS": 5,
  "STLNETWORK": 5,
  "STLTECH": 5,
  "STYLEBAAZA": 5,
  "SUBEXLTD": 5,
  "SUMEETINDS": 5,
  "SUMIT": 5,
  "SUNDRMBRAK": 5,
  "SUNLITE": 5,
  "SUNTECH": 5,
  "SUPREMEPWR": 5,
  "SUTLEJTEX": 5,
  "SVPGLOB": 5,
  "SWANDEF": 5,
  "SYLVANPLY": 5,
  "SYNOPTICS": 5,
  "SYSTMTXC": 5,
  "TAC": 5,
  "TAKE": 5,
  "TAMBOLIIN": 5,
  "TAPIFRUIT": 5,
  "TARAPUR": 5,
  "TCIFINANCE": 5,
  "TECHD": 5,
  "TECHERA": 5,
  "TECHLABS": 5,
  "TEJASCARGO": 5,
  "TERASOFT": 5,
  "TGL": 5,
  "THACKER": 5,
  "THAKDEV": 5,
  "THESL": 5,
  "TICL": 5,
  "TIGERLOGS": 5,
  "TIMESCAN": 5,
  "TIRUPATI": 5,
  "TOKYOPLAST": 5,
  "TRANSWIND": 5,
  "TRANSWORLD": 5,
  "TRIDHYA": 5,
  "TRIVENI": 5,
  "TROM": 5,
  "TRU": 5,
  "UFBL": 5,
  "UMAEXPORTS": 5,
  "UMESLTD": 5,
  "UNIDT": 5,
  "UNIINFO": 5,
  "UNITECH": 5,
  "UNITEDPOLY": 5,
  "UNIVASTU": 5,
  "UNIVPHOTO": 5,
  "URAVIDEF": 5,
  "USASEEDS": 5,
  "UTKAL": 5,
  "UTSSAV": 5,
  "UWCSL": 5,
  "VAISHALI": 5,
  "VALIANTLAB": 5,
  "VALIANTORG": 5,
  "VARDHACRLC": 5,
  "VASA": 5,
  "VASCONEQ": 5,
  "VCL": 5,
  "VEEKAYEM": 5,
  "VELJAN": 5,
  "VELS": 5,
  "VENUSREM": 5,
  "VERA": 5,
  "VERITAAS": 5,
  "VERTEXPLUS": 5,
  "VERTOZ": 5,
  "VETO": 5,
  "VHLTD": 5,
  "VIAZ": 5,
  "VICTORYEV": 5,
  "VIDYAWIRES": 5,
  "VIGOR": 5,
  "VILINBIO": 5,
  "VINEETLAB": 5,
  "VINSYS": 5,
  "VIPCLOTHNG": 5,
  "VIPULLTD": 5,
  "VISACHROME": 5,
  "VISHWAS": 5,
  "VISL": 5,
  "VIVIANA": 5,
  "VIVIDEL": 5,
  "VIVIMEDLAB": 5,
  "VIVO": 5,
  "VLINFRA": 5,
  "VMSTMT": 5,
  "VR": 5,
  "VSCL": 5,
  "WAAREEINDO": 5,
  "WALPAR": 5,
  "WEBELSOLAR": 5,
  "WELINV": 5,
  "WEWIN": 5,
  "WHITEFORCE": 5,
  "WINNY": 5,
  "WOL3D": 5,
  "YAAP": 5,
  "YUDIZ": 5,
  "ZEELEARN": 5,
  "ZENITHEXPO": 5,
  "ZODIAC": 5,
  "A2ZINFRA": 10,
  "ABDL": 10,
  "ABMINTLLTD": 10,
  "ACL": 10,
  "ACMESOLAR": 10,
  "AEGISLOG": 10,
  "AEGISVOPAK": 10,
  "AEPL": 10,
  "AEROFLEX": 10,
  "AFIL": 10,
  "AGL": 10,
  "AJAXENGG": 10,
  "AKUMS": 10,
  "AMBAAUTO": 10,
  "ARTNIRMAN": 10,
  "ATLASCYCLE": 10,
  "BAJAJHFL": 10,
  "BANSALWIRE": 10,
  "BBOX": 10,
  "BEWLTD": 10,
  "BLBLIMITED": 10,
  "BLUEJET": 10,
  "BLUSPRING": 10,
  "BOSCH-HCIL": 10,
  "C2C": 10,
  "CEIGALL": 10,
  "CKKRETAIL": 10,
  "CMRGREEN": 10,
  "COCKERILL": 10,
  "CONFIPET": 10,
  "CORDELIA": 10,
  "COUNCODOS": 10,
  "CRIZAC": 10,
  "CTE": 10,
  "CURAA": 10,
  "DENEERS": 10,
  "DIACABS": 10,
  "DIGITIDE": 10,
  "DJML": 10,
  "DUCON": 10,
  "EFORCE": 10,
  "ELECTHERM": 10,
  "ELGNZ": 10,
  "ELLEN": 10,
  "ELPROINTL": 10,
  "EMBDL": 10,
  "EMCURE": 10,
  "EMMVEE": 10,
  "EMSLIMITED": 10,
  "ENSER": 10,
  "ESCONET": 10,
  "FALCONTECH": 10,
  "FCL": 10,
  "FINBUD": 10,
  "FISCHER": 10,
  "FLAIR": 10,
  "FORCAS": 10,
  "GANGABATH": 10,
  "GAYAHWS": 10,
  "GENESYS": 10,
  "GKENERGY": 10,
  "GOPAL": 10,
  "GRMOVER": 10,
  "GRWRHITECH": 10,
  "GSS": 10,
  "GTL": 10,
  "GUJALKALI": 10,
  "HAPPYFORGE": 10,
  "HARDWYN": 10,
  "HAVISHA": 10,
  "HEXATRADEX": 10,
  "ICDSLTD": 10,
  "ICICIAMC": 10,
  "IGIL": 10,
  "IRMENERGY": 10,
  "ITALIANE": 10,
  "JAYBEE": 10,
  "JHS": 10,
  "JSWHL": 10,
  "JSWINFRA": 10,
  "JUNIPER": 10,
  "JUSTDIAL": 10,
  "JYOTIGLOBL": 10,
  "KALANA": 10,
  "KALPATARU": 10,
  "KAMOPAINTS": 10,
  "KANDARP": 10,
  "KARMAENG": 10,
  "KAVDEFENCE": 10,
  "KCK": 10,
  "KODYTECH": 10,
  "KORE": 10,
  "KREBSBIO": 10,
  "KUSUMGAR": 10,
  "LANCORHOL": 10,
  "LASA": 10,
  "LASERPOWER": 10,
  "LAXMICOT": 10,
  "LEXUS": 10,
  "LGEINDIA": 10,
  "LIKHITHA": 10,
  "LOTUSDEV": 10,
  "LOYALTEX": 10,
  "LPDC": 10,
  "LRRPL": 10,
  "LUXIND": 10,
  "MAGNUM": 10,
  "MCL": 10,
  "MIDWESTLTD": 10,
  "MODTHREAD": 10,
  "MSTCLTD": 10,
  "MVKAGRO": 10,
  "NIBE": 10,
  "NIRAJISPAT": 10,
  "NIRMAN": 10,
  "NPST": 10,
  "OSWALPUMPS": 10,
  "PANACEABIO": 10,
  "PANAMAPET": 10,
  "PARACABLES": 10,
  "PARAS": 10,
  "PARASPETRO": 10,
  "PARKHOSPS": 10,
  "PNC": 10,
  "PNGJL": 10,
  "POLYSIL": 10,
  "PRESSTONIC": 10,
  "RACE": 10,
  "RADIOCITY": 10,
  "RAJMET": 10,
  "RAMCOSYS": 10,
  "RKEC": 10,
  "SAATVIKGL": 10,
  "SADBHAV": 10,
  "SAKAR": 10,
  "SAKSOFT": 10,
  "SAMBHAAV": 10,
  "SANATHAN": 10,
  "SARTELE": 10,
  "SBIFUNDS": 10,
  "SCHNEIDER": 10,
  "SCML": 10,
  "SECMARK": 10,
  "SECURKLOUD": 10,
  "SEL": 10,
  "SGL": 10,
  "SHIVAUM": 10,
  "SHREEJISPG": 10,
  "SILKY": 10,
  "SONAMAC": 10,
  "SPARC": 10,
  "STUDIOLSD": 10,
  "STYL": 10,
  "SUDEEPPHRM": 10,
  "SUNFLAG": 10,
  "SURANI": 10,
  "SUVIDHAA": 10,
  "TARMAT": 10,
  "TATACAP": 10,
  "THANGAMAYL": 10,
  "THELEELA": 10,
  "TIJARIA": 10,
  "TIRUPATIFL": 10,
  "TRAVELFOOD": 10,
  "TREEHOUSE": 10,
  "TREJHARA": 10,
  "TTL": 10,
  "TVSSCS": 10,
  "UNICHEMLAB": 10,
  "UNIHEALTH": 10,
  "UNIMECH": 10,
  "USK": 10,
  "UTLSOLAR": 10,
  "VENTIVE": 10,
  "VIKASECO": 10,
  "VIKASLIFE": 10,
  "VIRINCHI": 10,
  "VISAMAN": 10,
  "VISHWARAJ": 10,
  "VIVIDHA": 10,
  "VMOBILE": 10,
  "WEL": 10,
  "WELSPLSOL": 10,
  "WTICAB": 10,
  "ZEEMEDIA": 10,
  "ZENITHSTL": 10,
  "ZSARACOM": 10,
  "20MICRONS": 20,
  "3BBLACKBIO": 20,
  "3IINFOLTD": 20,
  "3MINDIA": 20,
  "3PLAND": 20,
  "5PAISA": 20,
  "63MOONS": 20,
  "AAATECH": 20,
  "AADHARHFC": 20,
  "AAKASH": 20,
  "AARADHYA": 20,
  "AARNAV": 20,
  "AARON": 20,
  "AARTIDRUGS": 20,
  "AARTIIND": 20,
  "AARTIPHARM": 20,
  "AARTISURF": 20,
  "AARVI": 20,
  "AASTHA": 20,
  "AATMAJ": 20,
  "AAVAS": 20,
  "ABBOTINDIA": 20,
  "ABCOTS": 20,
  "ABFRL": 20,
  "ABGSEC": 20,
  "ABHAPOWER": 20,
  "ABINFRA": 20,
  "ABLBL": 20,
  "ABMKNO": 20,
  "ABNINT": 20,
  "ABREL": 20,
  "ABSL10BANK": 20,
  "ABSLAMC": 20,
  "ABSLBANETF": 20,
  "ABSLMSCIN": 20,
  "ABSLNN50ET": 20,
  "ABSLPSE": 20,
  "ACC": 20,
  "ACCELYA": 20,
  "ACCENTMIC": 20,
  "ACE": 20,
  "ACEINTEG": 20,
  "ACETEC": 20,
  "ACI": 20,
  "ACTIVEINFR": 20,
  "ACUTAAS": 20,
  "ADFFOODS": 20,
  "ADISOFT": 20,
  "ADL": 20,
  "ADOR": 20,
  "ADROITINFO": 20,
  "ADSL": 20,
  "ADVAIT": 20,
  "ADVANCE": 20,
  "ADVANIHOTR": 20,
  "ADVENTHTL": 20,
  "ADVENZYMES": 20,
  "AEQUS": 20,
  "AEROENTER": 20,
  "AERON": 20,
  "AERONEU": 20,
  "AESTHETIK": 20,
  "AETHER": 20,
  "AFCONS": 20,
  "AFFLE": 20,
  "AFSL": 20,
  "AGARIND": 20,
  "AGARWALEYE": 20,
  "AGARWALTUF": 20,
  "AGI": 20,
  "AGIIL": 20,
  "AGROPHOS": 20,
  "AHCL": 20,
  "AHLADA": 20,
  "AHLEAST": 20,
  "AHLUCONT": 20,
  "AIAENG": 20,
  "AIIL": 20,
  "AIMTRON": 20,
  "AIRAN": 20,
  "AIROLAM": 20,
  "AJANTPHARM": 20,
  "AJMERA": 20,
  "AJOONI": 20,
  "AKASH": 20,
  "AKCAPIT": 20,
  "AKG": 20,
  "AKI": 20,
  "AKSHAR": 20,
  "ALANKIT": 20,
  "ALBERTDAVD": 20,
  "ALEMBICLTD": 20,
  "ALGOQUANT": 20,
  "ALICON": 20,
  "ALIVUS": 20,
  "ALKYLAMINE": 20,
  "ALLCARGO": 20,
  "ALLDIGI": 20,
  "ALLTIME": 20,
  "ALMONDZ": 20,
  "ALOKINDS": 20,
  "ALPA": 20,
  "ALPEXSOLAR": 20,
  "ALPHA": 20,
  "ALPHAETF": 20,
  "ALPHAGEO": 20,
  "ALPL30IETF": 20,
  "ALUWIND": 20,
  "AMAGI": 20,
  "AMBALALSA": 20,
  "AMBICAAGAR": 20,
  "AMBIKCO": 20,
  "AMCL": 20,
  "AMDIND": 20,
  "AMIABLE": 20,
  "AMJLAND": 20,
  "AMNPLST": 20,
  "AMRUTANJAN": 20,
  "ANANDRATHI": 20,
  "ANANTAM": 20,
  "ANANTRAJ": 20,
  "ANDHRAPAP": 20,
  "ANDHRSUGAR": 20,
  "ANMOL": 20,
  "ANNAPURNA": 20,
  "ANONDITA": 20,
  "ANTGRAPHIC": 20,
  "ANTHEM": 20,
  "ANUHPHR": 20,
  "ANUP": 20,
  "ANURAS": 20,
  "ANYA": 20,
  "ANZEN": 20,
  "AONEGOLD": 20,
  "AONENIFTY": 20,
  "AONESILVER": 20,
  "AONETMMQ50": 20,
  "AONETOTAL": 20,
  "APARINDS": 20,
  "APCL": 20,
  "APCOTEXIND": 20,
  "APEX": 20,
  "APLLTD": 20,
  "APOLLO": 20,
  "APOLLOPIPE": 20,
  "APOLLOTYRE": 20,
  "APOLSINHOT": 20,
  "APRAMEYA": 20,
  "APS": 20,
  "APTUS": 20,
  "ARABIAN": 20,
  "ARCHIDPLY": 20,
  "ARCHIES": 20,
  "ARE&M": 20,
  "ARENTERP": 20,
  "ARFIN": 20,
  "ARHAM": 20,
  "ARIES": 20,
  "ARIHANT": 20,
  "ARIHANTACA": 20,
  "ARIHANTCAP": 20,
  "ARIHANTSUP": 20,
  "ARIS": 20,
  "ARKADE": 20,
  "ARMANFIN": 20,
  "AROGRANITE": 20,
  "ARSSBL": 20,
  "ARTEMISMED": 20,
  "ARVEE": 20,
  "ARVIND": 20,
  "ARVINDFASN": 20,
  "ARVSMART": 20,
  "ASAHIINDIA": 20,
  "ASAHISONG": 20,
  "ASAL": 20,
  "ASALCBR": 20,
  "ASHALOG": 20,
  "ASHAPURMIN": 20,
  "ASHIANA": 20,
  "ASHIKA": 20,
  "ASHIMASYN": 20,
  "ASHOKA": 20,
  "ASHOKAMET": 20,
  "ASHWINI": 20,
  "ASIANENE": 20,
  "ASIANHOTNR": 20,
  "ASIANTILES": 20,
  "ASKAUTOLTD": 20,
  "ASPINWALL": 20,
  "ASTAR": 20,
  "ASTEC": 20,
  "ASTERDM": 20,
  "ASTRAMICRO": 20,
  "ASTRAZEN": 20,
  "ATALREAL": 20,
  "ATAM": 20,
  "ATGL": 20,
  "ATHERENERG": 20,
  "ATL": 20,
  "ATLANTAA": 20,
  "ATLPP": 20,
  "ATUL": 20,
  "ATULAUTO": 20,
  "AURIONPRO": 20,
  "AURUM": 20,
  "AURUS": 20,
  "AUTOAXLES": 20,
  "AUTOBEES": 20,
  "AUTOIETF": 20,
  "AVALON": 20,
  "AVANTEL": 20,
  "AVANTIFEED": 20,
  "AVIANSH": 20,
  "AVIENCE": 20,
  "AVL": 20,
  "AVONMORE": 20,
  "AVROIND": 20,
  "AVTNPL": 20,
  "AWFIS": 20,
  "AWHCL": 20,
  "AWL": 20,
  "AXITA": 20,
  "AYE": 20,
  "AYMSYNTEX": 20,
  "AZAD": 20,
  "BABAFP": 20,
  "BAGDIGITAL": 20,
  "BAGFILMS": 20,
  "BAGMANE": 20,
  "BAHETI": 20,
  "BAIDFIN": 20,
  "BAJAJCON": 20,
  "BAJAJELEC": 20,
  "BAJAJHCARE": 20,
  "BAJAJHIND": 20,
  "BAJAJINDEF": 20,
  "BAJAJST": 20,
  "BAJEL": 20,
  "BALAJEE": 20,
  "BALAJIPHOS": 20,
  "BALAJITELE": 20,
  "BALAMINES": 20,
  "BALKRISHNA": 20,
  "BALKRISIND": 20,
  "BALMLAWRIE": 20,
  "BALPHARMA": 20,
  "BALRAMCHIN": 20,
  "BALUFORGE": 20,
  "BANARBEADS": 20,
  "BANARISUG": 20,
  "BANCOINDIA": 20,
  "BANG": 20,
  "BANK10ADD": 20,
  "BANK10BETF": 20,
  "BANKADD": 20,
  "BANKBEES": 20,
  "BANKBETA": 20,
  "BANKBETF": 20,
  "BANKETF": 20,
  "BANKIETF": 20,
  "BANKNIFTY1": 20,
  "BANKPSU": 20,
  "BANSWRAS": 20,
  "BARFLEX": 20,
  "BASF": 20,
  "BASILIC": 20,
  "BATAINDIA": 20,
  "BATLIBOI": 20,
  "BAYERCROP": 20,
  "BBETF0432": 20,
  "BBL": 20,
  "BBNPNBETF": 20,
  "BBNPPGOLD": 20,
  "BBTC": 20,
  "BBTCL": 20,
  "BCG": 20,
  "BCLIND": 20,
  "BCONCEPTS": 20,
  "BCPL": 20,
  "BEARDSELL": 20,
  "BECTORFOOD": 20,
  "BEEKAY": 20,
  "BELLACASA": 20,
  "BELRISE": 20,
  "BEML": 20,
  "BENGALASM": 20,
  "BEPL": 20,
  "BERGEPAINT": 20,
  "BESTAGRO": 20,
  "BETA": 20,
  "BFINVEST": 20,
  "BFSI": 20,
  "BFUTILITIE": 20,
  "BHAGCHEM": 20,
  "BHARATCOAL": 20,
  "BHARATRAS": 20,
  "BHARATSE": 20,
  "BHARATWIRE": 20,
  "BHARTIHEXA": 20,
  "BI": 20,
  "BIGBLOC": 20,
  "BIKAJI": 20,
  "BIL": 20,
  "BIMETAL": 20,
  "BIOFILCHEM": 20,
  "BIOPOL": 20,
  "BIRET": 20,
  "BIRLACORPN": 20,
  "BIRLAMONEY": 20,
  "BIRLANU": 20,
  "BIRLAPREC": 20,
  "BLACKBUCK": 20,
  "BLAL": 20,
  "BLIL": 20,
  "BLKASHYAP": 20,
  "BLS": 20,
  "BLSE": 20,
  "BLUEDART": 20,
  "BLUEPEBBLE": 20,
  "BLUESTONE": 20,
  "BMETRICS": 20,
  "BMLL": 20,
  "BMWVENTLTD": 20,
  "BNKETFAXIS": 20,
  "BOMDYEING": 20,
  "BORANA": 20,
  "BOROLTD": 20,
  "BORORENEW": 20,
  "BOROSCI": 20,
  "BPL": 20,
  "BRACEPORT": 20,
  "BRIGADE": 20,
  "BRIGHOTEL": 20,
  "BRNL": 20,
  "BSE500IETF": 20,
  "BSL": 20,
  "BSLGOLDETF": 20,
  "BSLNIFTY": 20,
  "BSLSENETFG": 20,
  "BSOFT": 20,
  "BTML": 20,
  "BUILDPRO": 20,
  "BUTTERFLY": 20,
  "BVCL": 20,
  "CAMLINFINE": 20,
  "CAMPUS": 20,
  "CANARYS": 20,
  "CANFINHOME": 20,
  "CANHLIFE": 20,
  "CANTABIL": 20,
  "CAPACITE": 20,
  "CAPILLARY": 20,
  "CAPINVIT": 20,
  "CAPITALSFB": 20,
  "CAPLIPOINT": 20,
  "CARBORUNIV": 20,
  "CARERATING": 20,
  "CARRARO": 20,
  "CARTRADE": 20,
  "CARYSIL": 20,
  "CASTROLIND": 20,
  "CCAVENUE": 20,
  "CCCL": 20,
  "CCHHL": 20,
  "CCL": 20,
  "CEATLTD": 20,
  "CEINSYS": 20,
  "CELEBRITY": 20,
  "CELLO": 20,
  "CELLPOINT": 20,
  "CENTENKA": 20,
  "CENTEXT": 20,
  "CENTRALBK": 20,
  "CENTRUM": 20,
  "CENTUM": 20,
  "CENTURYPLY": 20,
  "CERA": 20,
  "CESC": 20,
  "CEWATER": 20,
  "CGCL": 20,
  "CGRAPHICS": 20,
  "CHALET": 20,
  "CHAMBLFERT": 20,
  "CHAMUNDA": 20,
  "CHANDAN": 20,
  "CHAVDA": 20,
  "CHEMICAL": 20,
  "CHEMPLASTS": 20,
  "CHENNPETRO": 20,
  "CHEVIOT": 20,
  "CHOICEGOLD": 20,
  "CHOICEIN": 20,
  "CHOLAHLDNG": 20,
  "CIEINDIA": 20,
  "CIFL": 20,
  "CINELINE": 20,
  "CINEVISTA": 20,
  "CITIUSINVT": 20,
  "CLAYCRAFT": 20,
  "CLEAN": 20,
  "CLEANMAX": 20,
  "CLSEL": 20,
  "CLSL": 20,
  "CMNL": 20,
  "CMPDI": 20,
  "CMSINFO": 20,
  "CNL": 20,
  "COASTCORP": 20,
  "COHANCE": 20,
  "COMFINTE": 20,
  "COMMOIETF": 20,
  "COMPUSOFT": 20,
  "COMSYN": 20,
  "CONCORDBIO": 20,
  "CONNPLEX": 20,
  "CONS": 20,
  "CONSOFINVT": 20,
  "CONSUMAXIS": 20,
  "CONSUMBEES": 20,
  "CONSUMER": 20,
  "CONSUMIETF": 20,
  "CONTROLPR": 20,
  "CORALFINAC": 20,
  "COROMANDEL": 20,
  "CORONA": 20,
  "COSMOFIRST": 20,
  "CPEDU": 20,
  "CPSEETF": 20,
  "CRAFTSMAN": 20,
  "CRAMC": 20,
  "CREATIVEYE": 20,
  "CREDITACC": 20,
  "CREST": 20,
  "CRISIL": 20,
  "CROWN": 20,
  "CSBBANK": 20,
  "CSLFINANCE": 20,
  "CSM": 20,
  "CSSL": 20,
  "CUB": 20,
  "CUBEINVIT": 20,
  "CUBEXTUB": 20,
  "CUPID": 20,
  "CURIS": 20,
  "CURRENT": 20,
  "CYIENT": 20,
  "CYIENTDLM": 20,
  "DALMIASUG": 20,
  "DAMCAPITAL": 20,
  "DANISH": 20,
  "DATAMATICS": 20,
  "DATAPATTNS": 20,
  "DAVANGERE": 20,
  "DBCORP": 20,
  "DBL": 20,
  "DBOL": 20,
  "DCAL": 20,
  "DCBBANK": 20,
  "DCCL": 20,
  "DCG": 20,
  "DCI": 20,
  "DCMSHRIRAM": 20,
  "DCMSRIND": 20,
  "DCW": 20,
  "DCXINDIA": 20,
  "DDEVPLSTIK": 20,
  "DECCANCE": 20,
  "DECCANTRAN": 20,
  "DECNGOLD": 20,
  "DEEPAKFERT": 20,
  "DEEPAKNTR": 20,
  "DEEPINDS": 20,
  "DEFENCE": 20,
  "DELAPLEX": 20,
  "DELTACORP": 20,
  "DELTAMAGNT": 20,
  "DEN": 20,
  "DENORA": 20,
  "DENTA": 20,
  "DENTALKART": 20,
  "DEVIT": 20,
  "DEVX": 20,
  "DEVYANI": 20,
  "DGCONTENT": 20,
  "DHAMPURSUG": 20,
  "DHANBANK": 20,
  "DHANLAXMI": 20,
  "DHANUKA": 20,
  "DHARIWAL": 20,
  "DHARMAJ": 20,
  "DHUNINV": 20,
  "DIAMINESQ": 20,
  "DIAMONDYD": 20,
  "DICIND": 20,
  "DIFFNKG": 20,
  "DIGIDRIVE": 20,
  "DIGIKORE": 20,
  "DIGJAMLMTD": 20,
  "DISAQ": 20,
  "DIVGIITTS": 20,
  "DIVIDEND": 20,
  "DIVOPPBEES": 20,
  "DKEGL": 20,
  "DLINKINDIA": 20,
  "DMCC": 20,
  "DNAMEDIA": 20,
  "DODLA": 20,
  "DOLATALGO": 20,
  "DOLLAR": 20,
  "DOLLEX": 20,
  "DOLPHIN": 20,
  "DOMS": 20,
  "DONEAR": 20,
  "DPABHUSHAN": 20,
  "DRAGARWQ": 20,
  "DRCSYSTEMS": 20,
  "DREAMFOLKS": 20,
  "DREDGECORP": 20,
  "DTIL": 20,
  "DTL": 20,
  "DUCOL": 20,
  "DVL": 20,
  "DWARKESH": 20,
  "DYCL": 20,
  "DYNAMATECH": 20,
  "DYNPRO": 20,
  "EASEMYTRIP": 20,
  "EBANKNIFTY": 20,
  "EBBETF0430": 20,
  "EBBETF0431": 20,
  "EBBETF0433": 20,
  "ECAPINSURE": 20,
  "ECLERX": 20,
  "EDELWEISS": 20,
  "EEPL": 20,
  "EFACTOR": 20,
  "EFCIL": 20,
  "EGOLD": 20,
  "EIDPARRY": 20,
  "EIEL": 20,
  "EIHAHOTELS": 20,
  "EIHOTEL": 20,
  "EIMCOELECO": 20,
  "EKC": 20,
  "ELANTAS": 20,
  "ELCIDIN": 20,
  "ELDEHSG": 20,
  "ELECON": 20,
  "ELECTCAST": 20,
  "ELGIEQUIP": 20,
  "ELGIRUBCO": 20,
  "ELIN": 20,
  "ELITECON": 20,
  "ELM250": 20,
  "EMAMILTD": 20,
  "EMAMIPAP": 20,
  "EMAPARTNER": 20,
  "EMBASSY": 20,
  "EMIL": 20,
  "EMKAY": 20,
  "EMKAYTOOLS": 20,
  "EMMIL": 20,
  "EMUDHRA": 20,
  "EMULTIMQ": 20,
  "ENCOMPAS": 20,
  "ENDURANCE": 20,
  "ENERGY": 20,
  "ENERGYDEV": 20,
  "ENEXT50": 20,
  "ENFUSE": 20,
  "ENGINERSIN": 20,
  "ENIFTY": 20,
  "ENIL": 20,
  "ENRIN": 20,
  "ENTERO": 20,
  "ENVIRO": 20,
  "EPACK": 20,
  "EPACKPEB": 20,
  "EPIGRAL": 20,
  "EPL": 20,
  "EQUAL200": 20,
  "EQUAL50": 20,
  "EQUAL50ADD": 20,
  "EQUITASBNK": 20,
  "ERIS": 20,
  "ESABINDIA": 20,
  "ESAFSFB": 20,
  "ESCORTS": 20,
  "ESENSEX": 20,
  "ESG": 20,
  "ESILVER": 20,
  "ESPRIT": 20,
  "ESSARSHPNG": 20,
  "ESTER": 20,
  "ETHOSLTD": 20,
  "ETL": 20,
  "ETML": 20,
  "EUREKAFORB": 20,
  "EUROBOND": 20,
  "EUROPRATIK": 20,
  "EVEREADY": 20,
  "EVIETF": 20,
  "EVINDIA": 20,
  "EXCELINDUS": 20,
  "EXCELSOFT": 20,
  "EXICOM": 20,
  "EXIMROUTES": 20,
  "EXPLEOSOL": 20,
  "EXXARO": 20,
  "FABTECH": 20,
  "FACT": 20,
  "FDC": 20,
  "FEDDERSHOL": 20,
  "FEDFINA": 20,
  "FELIX": 20,
  "FERMENTA": 20,
  "FIDEL": 20,
  "FIEMIND": 20,
  "FILATEX": 20,
  "FINCABLES": 20,
  "FINEORG": 20,
  "FINIETF": 20,
  "FINKURVE": 20,
  "FINOPB": 20,
  "FINPIPE": 20,
  "FIRSTCRY": 20,
  "FIVESTAR": 20,
  "FLEXIADD": 20,
  "FLUOROCHEM": 20,
  "FLYSBS": 20,
  "FMCGADD": 20,
  "FMCGIETF": 20,
  "FMGOETZE": 20,
  "FOODSIN": 20,
  "FOSECOIND": 20,
  "FRACTAL": 20,
  "FRESHARA": 20,
  "FRONTSP": 20,
  "FSL": 20,
  "FUSION": 20,
  "FWSTC": 20,
  "GABRIEL": 20,
  "GAEL": 20,
  "GAJANAND": 20,
  "GALAPREC": 20,
  "GALAXYSURF": 20,
  "GANDHAR": 20,
  "GANDHITUBE": 20,
  "GANECOS": 20,
  "GANESHBE": 20,
  "GANESHCP": 20,
  "GANESHHOU": 20,
  "GANGESSECU": 20,
  "GARFIBRES": 20,
  "GARUDA": 20,
  "GATECH": 20,
  "GATECHDVR": 20,
  "GATEWAY": 20,
  "GCSL": 20,
  "GEEKAYWIRE": 20,
  "GEMAROMA": 20,
  "GENCON": 20,
  "GENUSPAPER": 20,
  "GENUSPOWER": 20,
  "GENXAI": 20,
  "GEOJITFSL": 20,
  "GESHIP": 20,
  "GFLLIMITED": 20,
  "GGBL": 20,
  "GHCL": 20,
  "GHCLTEXTIL": 20,
  "GICHSGFIN": 20,
  "GICRE": 20,
  "GILLANDERS": 20,
  "GILLETTE": 20,
  "GIPCL": 20,
  "GKSL": 20,
  "GKWLIMITED": 20,
  "GLAND": 20,
  "GLAXO": 20,
  "GLOBAL": 20,
  "GLOBALVECT": 20,
  "GLOBE": 20,
  "GLOBUSSPR": 20,
  "GLOSTERLTD": 20,
  "GMBREW": 20,
  "GMDCLTD": 20,
  "GMMPFAUDLR": 20,
  "GMRP&UI": 20,
  "GNA": 20,
  "GNFC": 20,
  "GNRL": 20,
  "GOACARBON": 20,
  "GOCLCORP": 20,
  "GOCOLORS": 20,
  "GODAVARIB": 20,
  "GODIGIT": 20,
  "GODREJAGRO": 20,
  "GODREJIND": 20,
  "GOKEX": 20,
  "GOKUL": 20,
  "GOKULAGRO": 20,
  "GOLD1": 20,
  "GOLD360": 20,
  "GOLDADD": 20,
  "GOLDAXIS": 20,
  "GOLDBEES": 20,
  "GOLDBETA": 20,
  "GOLDBND": 20,
  "GOLDCASE": 20,
  "GOLDETF": 20,
  "GOLDIAM": 20,
  "GOLDIETF": 20,
  "GOODLUCK": 20,
  "GOODYEAR": 20,
  "GOYALALUM": 20,
  "GOYALSALT": 20,
  "GPIL": 20,
  "GPPL": 20,
  "GPTHEALTH": 20,
  "GPTINFRA": 20,
  "GRANULES": 20,
  "GRAPHITE": 20,
  "GRAUWEIL": 20,
  "GRAVISSHO": 20,
  "GRAVITA": 20,
  "GREAVESCOT": 20,
  "GREENLAM": 20,
  "GREENPANEL": 20,
  "GREENPLY": 20,
  "GREENPOWER": 20,
  "GRINDWELL": 20,
  "GRINFRA": 20,
  "GROBTEA": 20,
  "GROWW": 20,
  "GROWWCAPM": 20,
  "GROWWCHEM": 20,
  "GROWWDEFNC": 20,
  "GROWWEV": 20,
  "GROWWGOLD": 20,
  "GROWWHOSPI": 20,
  "GROWWLOVOL": 20,
  "GROWWMC150": 20,
  "GROWWMETAL": 20,
  "GROWWMOM50": 20,
  "GROWWN200": 20,
  "GROWWNET": 20,
  "GROWWNIFTY": 20,
  "GROWWNXT50": 20,
  "GROWWPOWER": 20,
  "GROWWPSE": 20,
  "GROWWPSUBK": 20,
  "GROWWRAIL": 20,
  "GROWWRLTY": 20,
  "GROWWSC250": 20,
  "GROWWSLVR": 20,
  "GRPLTD": 20,
  "GRSE": 20,
  "GSEC10ABSL": 20,
  "GSFC": 20,
  "GSMFOILS": 20,
  "GSPCROP": 20,
  "GTLINFRA": 20,
  "GTPL": 20,
  "GUFICBIO": 20,
  "GUJAPOLLO": 20,
  "GUJENERGY": 20,
  "GUJTHEM": 20,
  "GULFOILLUB": 20,
  "GULPOLY": 20,
  "GVPTECH": 20,
  "GYFTR": 20,
  "HALDER": 20,
  "HALEOSLABS": 20,
  "HAPPSTMNDS": 20,
  "HARIOMPIPE": 20,
  "HARRMALAYA": 20,
  "HARSHA": 20,
  "HATHWAY": 20,
  "HATSUN": 20,
  "HAWKINCOOK": 20,
  "HBESD": 20,
  "HBLENGINE": 20,
  "HCC": 20,
  "HCG": 20,
  "HCL-INSYS": 20,
  "HDBFS": 20,
  "HDFCBSE500": 20,
  "HDFCGOLD": 20,
  "HDFCGROWTH": 20,
  "HDFCLOWVOL": 20,
  "HDFCMID150": 20,
  "HDFCMOMENT": 20,
  "HDFCNEXT50": 20,
  "HDFCNIF100": 20,
  "HDFCNIFBAN": 20,
  "HDFCNIFIT": 20,
  "HDFCNIFTY": 20,
  "HDFCPSUBK": 20,
  "HDFCPVTBAN": 20,
  "HDFCQUAL": 20,
  "HDFCSENSEX": 20,
  "HDFCSILVER": 20,
  "HDFCSML250": 20,
  "HDFCVALUE": 20,
  "HEADSUP": 20,
  "HEALTHADD": 20,
  "HEALTHAXIS": 20,
  "HEALTHCARE": 20,
  "HEALTHIETF": 20,
  "HEALTHX": 20,
  "HEALTHY": 20,
  "HECPROJECT": 20,
  "HEG": 20,
  "HEIDELBERG": 20,
  "HEMIPROP": 20,
  "HERANBA": 20,
  "HERITGFOOD": 20,
  "HESTERBIO": 20,
  "HEXT": 20,
  "HGINFRA": 20,
  "HGM": 20,
  "HGS": 20,
  "HIGREEN": 20,
  "HIKAL": 20,
  "HIMATSEIDE": 20,
  "HINDCOMPOS": 20,
  "HINDCOPPER": 20,
  "HINDOILEXP": 20,
  "HINDWAREAP": 20,
  "HIRECT": 20,
  "HISARMETAL": 20,
  "HITECH": 20,
  "HLEGLAS": 20,
  "HLVLTD": 20,
  "HMAAGRO": 20,
  "HMVL": 20,
  "HNDFDS": 20,
  "HNGSNGBEES": 20,
  "HOMEFIRST": 20,
  "HONASA": 20,
  "HONAUT": 20,
  "HONDAPOWER": 20,
  "HPAL": 20,
  "HPIL": 20,
  "HPL": 20,
  "HSBCGOLD": 20,
  "HSCL": 20,
  "HTMEDIA": 20,
  "HUBTOWN": 20,
  "HUDCO": 20,
  "HUHTAMAKI": 20,
  "ICEMAKE": 20,
  "ICICIB22": 20,
  "ICIL": 20,
  "ICRA": 20,
  "IDBI": 20,
  "IDEALTECHO": 20,
  "IDENTICAL": 20,
  "IDFNIFTYET": 20,
  "IFBIND": 20,
  "IFCI": 20,
  "IFGLEXPOR": 20,
  "IGARASHI": 20,
  "IGCL": 20,
  "IGL": 20,
  "IGPL": 20,
  "IIFL": 20,
  "IIFLCAPS": 20,
  "IITL": 20,
  "IKIO": 20,
  "IKS": 20,
  "IMAGICAA": 20,
  "IMFA": 20,
  "IMPAL": 20,
  "INA": 20,
  "INCREDIBLE": 20,
  "INDBANK": 20,
  "INDGN": 20,
  "INDIACEM": 20,
  "INDIAGLYCO": 20,
  "INDIAMART": 20,
  "INDIANCARD": 20,
  "INDIANHUME": 20,
  "INDIASHLTR": 20,
  "INDIGOPNTS": 20,
  "INDIGRID": 20,
  "INDIQUBE": 20,
  "INDNIPPON": 20,
  "INDOBORAX": 20,
  "INDOCO": 20,
  "INDOFARM": 20,
  "INDORAMA": 20,
  "INDOSTAR": 20,
  "INDOTHAI": 20,
  "INDOUS": 20,
  "INDPRUD": 20,
  "INDRAMEDCO": 20,
  "INDSWFTLAB": 20,
  "INDTERRAIN": 20,
  "INDUSINVIT": 20,
  "INFLUX": 20,
  "INFOBEAN": 20,
  "INFOLLION": 20,
  "INFOMEDIA": 20,
  "INFRA": 20,
  "INFRABEES": 20,
  "INFRAIETF": 20,
  "INGERRAND": 20,
  "INM": 20,
  "INNOVACAP": 20,
  "INNOVANA": 20,
  "INNOVISION": 20,
  "INOXGREEN": 20,
  "INOXINDIA": 20,
  "INSECTICID": 20,
  "INTELLECT": 20,
  "INTENTECH": 20,
  "INTERARCH": 20,
  "INTERISE": 20,
  "INTERNET": 20,
  "INTLCONV": 20,
  "INVENTURE": 20,
  "INVPRECQ": 20,
  "IOB": 20,
  "IOLCP": 20,
  "IONEXCHANG": 20,
  "IPCALAB": 20,
  "IPHL": 20,
  "IPL": 20,
  "IPSL": 20,
  "IRB": 20,
  "IRBINVIT": 20,
  "IRBIT": 20,
  "IRCON": 20,
  "IRCTC": 20,
  "IRIS": 20,
  "IRISDOREME": 20,
  "ISFT": 20,
  "ISGEC": 20,
  "ISHANCH": 20,
  "IT": 20,
  "ITADD": 20,
  "ITAXIS": 20,
  "ITBEES": 20,
  "ITBETA": 20,
  "ITCHOTELS": 20,
  "ITDC": 20,
  "ITETF": 20,
  "ITI": 20,
  "ITIETF": 20,
  "IVALUE": 20,
  "IVC": 20,
  "IVZINGOLD": 20,
  "IVZINNIFTY": 20,
  "IWP": 20,
  "IXIGO": 20,
  "J&KBANK": 20,
  "JAGRAN": 20,
  "JAGSNPHARM": 20,
  "JAICORPLTD": 20,
  "JAINREC": 20,
  "JAIPURKURT": 20,
  "JAMNAAUTO": 20,
  "JARO": 20,
  "JASH": 20,
  "JAYAGROGN": 20,
  "JAYESH": 20,
  "JAYKAY": 20,
  "JAYNECOIND": 20,
  "JAYSREETEA": 20,
  "JBMA": 20,
  "JETFREIGHT": 20,
  "JGCHEM": 20,
  "JINDALPHOT": 20,
  "JINDALSAW": 20,
  "JINDRILL": 20,
  "JINDWORLD": 20,
  "JISLDVREQS": 20,
  "JISLJALEQS": 20,
  "JIWANRAM": 20,
  "JKCEMENT": 20,
  "JKIL": 20,
  "JKLAKSHMI": 20,
  "JKPAPER": 20,
  "JKTYRE": 20,
  "JLHL": 20,
  "JMA": 20,
  "JMFINANCIL": 20,
  "JNKINDIA": 20,
  "JPOLYINVST": 20,
  "JPPOWER": 20,
  "JSFB": 20,
  "JSL": 20,
  "JSLL": 20,
  "JSWCEMENT": 20,
  "JSWDULUX": 20,
  "JTEKTINDIA": 20,
  "JTLIND": 20,
  "JUBLCPL": 20,
  "JUBLINGREA": 20,
  "JUBLPHARMA": 20,
  "JUNIORBEES": 20,
  "JWL": 20,
  "JYOTHYLAB": 20,
  "JYOTICNC": 20,
  "JYOTISTRUC": 20,
  "KABRAEXTRU": 20,
  "KAJARIACER": 20,
  "KALAMANDIR": 20,
  "KALYANIFRG": 20,
  "KAMAHOLD": 20,
  "KAMATHOTEL": 20,
  "KANANIIND": 20,
  "KANPRPLA": 20,
  "KANSAINER": 20,
  "KAPSTON": 20,
  "KARNIKA": 20,
  "KARURVYSYA": 20,
  "KATARIA": 20,
  "KAYA": 20,
  "KAYTEX": 20,
  "KCP": 20,
  "KCPSUGIND": 20,
  "KDDL": 20,
  "KEC": 20,
  "KEEPLEARN": 20,
  "KEL": 20,
  "KELLTONTEC": 20,
  "KEN": 20,
  "KENNAMET": 20,
  "KERNEX": 20,
  "KEYFINSERV": 20,
  "KHANDSE": 20,
  "KHFM": 20,
  "KICL": 20,
  "KIMS": 20,
  "KINGFA": 20,
  "KIOCL": 20,
  "KIRANVYPAR": 20,
  "KIRIINDUS": 20,
  "KIRLFER": 20,
  "KIRLOSBROS": 20,
  "KIRLOSENG": 20,
  "KIRLOSIND": 20,
  "KIRLPNU": 20,
  "KISSHT": 20,
  "KITEX": 20,
  "KKCL": 20,
  "KKJEWELS": 20,
  "KLBRENG-B": 20,
  "KLL": 20,
  "KMEW": 20,
  "KMSUGAR": 20,
  "KNACK": 20,
  "KNAGRI": 20,
  "KNRCON": 20,
  "KOHINOOR": 20,
  "KOKUYOCMLN": 20,
  "KOLTEPATIL": 20,
  "KONTOR": 20,
  "KOTARISUG": 20,
  "KOTHARIPET": 20,
  "KOTHARIPRO": 20,
  "KOTIC": 20,
  "KOVAI": 20,
  "KPEL": 20,
  "KPIGREEN": 20,
  "KPIL": 20,
  "KPL": 20,
  "KPRMILL": 20,
  "KRBL": 20,
  "KRISHANA": 20,
  "KRISHCA": 20,
  "KRISHIVAL": 20,
  "KRISHNADEF": 20,
  "KRITIKA": 20,
  "KRONOX": 20,
  "KROSS": 20,
  "KRSNAA": 20,
  "KRT": 20,
  "KRYSTAL": 20,
  "KSB": 20,
  "KSCL": 20,
  "KSHINTL": 20,
  "KSL": 20,
  "KSOLVES": 20,
  "KTKBANK": 20,
  "KUANTUM": 20,
  "KWIL": 20,
  "LAGNAM": 20,
  "LAHOTIOV": 20,
  "LAL": 20,
  "LALPATHLAB": 20,
  "LAMBODHARA": 20,
  "LANDMARK": 20,
  "LANDSMILL": 20,
  "LAOPALA": 20,
  "LATENTVIEW": 20,
  "LAXMIDENTL": 20,
  "LEMONTREE": 20,
  "LENSKART": 20,
  "LFIC": 20,
  "LGBBROSLTD": 20,
  "LGHL": 20,
  "LIBAS": 20,
  "LIBERTSHOE": 20,
  "LICMFGOLD": 20,
  "LICNETFN50": 20,
  "LICNETFSEN": 20,
  "LICNFNHGP": 20,
  "LICNMID100": 20,
  "LINC": 20,
  "LINCOLN": 20,
  "LINDEINDIA": 20,
  "LLOYDSENGG": 20,
  "LLOYDSENT": 20,
  "LLOYDSME": 20,
  "LMW": 20,
  "LORDSCHLO": 20,
  "LOTUSEYE": 20,
  "LOVABLE": 20,
  "LOWVOL": 20,
  "LOWVOL1": 20,
  "LOWVOLIETF": 20,
  "LTFOODS": 20,
  "LTTS": 20,
  "LUMAXIND": 20,
  "LUMAXTECH": 20,
  "LXCHEM": 20,
  "M&MFIN": 20,
  "MAANALU": 20,
  "MACOBSTECH": 20,
  "MACPOWER": 20,
  "MADHAV": 20,
  "MADHAVIPL": 20,
  "MADRASFERT": 20,
  "MAFANG": 20,
  "MAFATIND": 20,
  "MAGADSUGAR": 20,
  "MAGSON": 20,
  "MAHABANK": 20,
  "MAHAPEXLTD": 20,
  "MAHASTEEL": 20,
  "MAHEPC": 20,
  "MAHICKRA": 20,
  "MAHKTECH": 20,
  "MAHLIFE": 20,
  "MAHLOG": 20,
  "MAHSCOOTER": 20,
  "MAHSEAMLES": 20,
  "MAITHANALL": 20,
  "MAITREYA": 20,
  "MAJESAUT": 20,
  "MAKEINDIA": 20,
  "MALLCOM": 20,
  "MALUPAPER": 20,
  "MAMATA": 20,
  "MANAKALUCO": 20,
  "MANAKCOAT": 20,
  "MANAKSIA": 20,
  "MANALIPETC": 20,
  "MANBA": 20,
  "MANCREDIT": 20,
  "MANGLMCEM": 20,
  "MANILAM": 20,
  "MANINDS": 20,
  "MANINFRA": 20,
  "MANOMAY": 20,
  "MANORAMA": 20,
  "MANUFGBEES": 20,
  "MANYAVAR": 20,
  "MAPMYINDIA": 20,
  "MARATHON": 20,
  "MARC": 20,
  "MARCO": 20,
  "MARINE": 20,
  "MARKOLINES": 20,
  "MARKSANS": 20,
  "MARSONS": 20,
  "MARUSHIKA": 20,
  "MASFIN": 20,
  "MASON": 20,
  "MASPTOP50": 20,
  "MASTEK": 20,
  "MASTERTR": 20,
  "MATRIMONY": 20,
  "MAXESTATES": 20,
  "MAXIND": 20,
  "MAXPOSURE": 20,
  "MAYASHEEL": 20,
  "MAYURUNIQ": 20,
  "MBAPL": 20,
  "MBEL": 20,
  "MCCHRLS-B": 20,
  "MCLOUD": 20,
  "MEDANTA": 20,
  "MEDIASSIST": 20,
  "MEDICAMEQ": 20,
  "MEDICO": 20,
  "MEDISTEP": 20,
  "MEDPLUS": 20,
  "MEESHO": 20,
  "MEGASTAR": 20,
  "MEGATHERM": 20,
  "MENNPIS": 20,
  "MERCANTILE": 20,
  "METAL": 20,
  "METALIETF": 20,
  "METROBRAND": 20,
  "METROGLOBL": 20,
  "METROPOLIS": 20,
  "MFML": 20,
  "MGL": 20,
  "MGSL": 20,
  "MHRIL": 20,
  "MICROPRO": 20,
  "MID150": 20,
  "MID150BEES": 20,
  "MID150CASE": 20,
  "MIDCAP": 20,
  "MIDCAPADD": 20,
  "MIDCAPBETA": 20,
  "MIDCAPETF": 20,
  "MIDCAPIETF": 20,
  "MIDHANI": 20,
  "MIDQ50ADD": 20,
  "MIDSELIETF": 20,
  "MIDSMALL": 20,
  "MINDACORP": 20,
  "MINDSPACE": 20,
  "MINDTECK": 20,
  "MIRZAINT": 20,
  "MITTAL": 20,
  "MKPL": 20,
  "MMFL": 20,
  "MMP": 20,
  "MMTC": 20,
  "MNC": 20,
  "MOALPHA50": 20,
  "MOBANK10": 20,
  "MOBIKWIK": 20,
  "MOCAPITAL": 20,
  "MODEFENCE": 20,
  "MODIRUBBER": 20,
  "MODIS": 20,
  "MOENERGY": 20,
  "MOGOLD": 20,
  "MOHEALTH": 20,
  "MOHITIND": 20,
  "MOIL": 20,
  "MOINFRA": 20,
  "MOIPO": 20,
  "MOKSH": 20,
  "MOL": 20,
  "MOLDTECH": 20,
  "MOLDTKPAC": 20,
  "MOLOWVOL": 20,
  "MOM100": 20,
  "MOM30IETF": 20,
  "MOM50": 20,
  "MOMENTUM": 20,
  "MOMENTUM30": 20,
  "MOMENTUM50": 20,
  "MOMGF": 20,
  "MOMIDMTM": 20,
  "MOMMIDCAP": 20,
  "MOMNC": 20,
  "MOMOMENTUM": 20,
  "MON100": 20,
  "MON50EQUAL": 20,
  "MONARCH": 20,
  "MONEXT50": 20,
  "MONEYBOXX": 20,
  "MONIFTY100": 20,
  "MONIFTY500": 20,
  "MONOLITH": 20,
  "MONQ50": 20,
  "MONTECARLO": 20,
  "MOPSE": 20,
  "MOQUALITY": 20,
  "MOREALTY": 20,
  "MOREPENLAB": 20,
  "MOSCHIP": 20,
  "MOSERVICE": 20,
  "MOSILVER": 20,
  "MOSMALL250": 20,
  "MOTISONS": 20,
  "MOTOUR": 20,
  "MOVALUE": 20,
  "MPSLTD": 20,
  "MRF": 20,
  "MRPL": 20,
  "MSCI360": 20,
  "MSCIADD": 20,
  "MSCIINDIA": 20,
  "MSUMI": 20,
  "MTNL": 20,
  "MUFIN": 20,
  "MUFTI": 20,
  "MUKANDLTD": 20,
  "MUKKA": 20,
  "MULTICAP": 20,
  "MUNJALAU": 20,
  "MUNJALSHOW": 20,
  "MURUDCERA": 20,
  "MUTHOOTCAP": 20,
  "MUTHOOTMF": 20,
  "MVGJL": 20,
  "MWL": 20,
  "MYMUDRA": 20,
  "NACLIND": 20,
  "NAGREEKEXP": 20,
  "NAHARCAP": 20,
  "NAHARINDUS": 20,
  "NAHARPOLY": 20,
  "NARMADA": 20,
  "NATCAPSUQ": 20,
  "NATCOPHARM": 20,
  "NATHBIOGEN": 20,
  "NAVA": 20,
  "NAVINFLUOR": 20,
  "NAVKARCORP": 20,
  "NAVNETEDUL": 20,
  "NAZARA": 20,
  "NBIFIN": 20,
  "NCC": 20,
  "NCLIND": 20,
  "NDGL": 20,
  "NDL": 20,
  "NDLVENTURE": 20,
  "NDRAUTO": 20,
  "NDRINVIT": 20,
  "NDTV": 20,
  "NELCAST": 20,
  "NELCO": 20,
  "NEOGEN": 20,
  "NEPHROPLUS": 20,
  "NEPTUNE": 20,
  "NESCO": 20,
  "NETF": 20,
  "NETWEB": 20,
  "NETWORK18": 20,
  "NEULANDLAB": 20,
  "NEWGEN": 20,
  "NEXT30ADD": 20,
  "NEXT50": 20,
  "NEXT50ADD": 20,
  "NEXT50BETA": 20,
  "NEXT50ETF": 20,
  "NEXT50IETF": 20,
  "NEXTMEDIA": 20,
  "NFL": 20,
  "NGLFINE": 20,
  "NH": 20,
  "NHIT": 20,
  "NIACL": 20,
  "NIBL": 20,
  "NIDAN": 20,
  "NIF100BEES": 20,
  "NIF100IETF": 20,
  "NIFTY1": 20,
  "NIFTY100EW": 20,
  "NIFTYADD": 20,
  "NIFTYAXIS": 20,
  "NIFTYBEES": 20,
  "NIFTYBETA": 20,
  "NIFTYBETF": 20,
  "NIFTYCASE": 20,
  "NIFTYETF": 20,
  "NIFTYIETF": 20,
  "NIFTYQLITY": 20,
  "NIITLTD": 20,
  "NIITMTS": 20,
  "NILAINFRA": 20,
  "NILASPACES": 20,
  "NILE": 20,
  "NILKAMAL": 20,
  "NIPPOBATRY": 20,
  "NIRLON": 20,
  "NITCO": 20,
  "NITINSPIN": 20,
  "NITIRAJ": 20,
  "NITTAGELA": 20,
  "NIVABUPA": 20,
  "NKIND": 20,
  "NLCINDIA": 20,
  "NMSTEEL": 20,
  "NOCIL": 20,
  "NORTHARC": 20,
  "NOVARTIND": 20,
  "NPBET": 20,
  "NRAIL": 20,
  "NRBBEARING": 20,
  "NSIL": 20,
  "NSLNISP": 20,
  "NTPCGREEN": 20,
  "NUCLEUS": 20,
  "NURECA": 20,
  "NUVOCO": 20,
  "NV20": 20,
  "NV20BEES": 20,
  "NV20IETF": 20,
  "NXST": 20,
  "NXT-INFRA": 20,
  "OAL": 20,
  "OBCL": 20,
  "OBSCP": 20,
  "OILIETF": 20,
  "OLAELEC": 20,
  "OLECTRA": 20,
  "OMAXE": 20,
  "OMINFRAL": 20,
  "OMNI": 20,
  "OMPOWER": 20,
  "ONDOOR": 20,
  "ONEPOINT": 20,
  "ONESOURCE": 20,
  "ONWARDTEC": 20,
  "OPTIEMUS": 20,
  "OPTIVALUE": 20,
  "ORCHASP": 20,
  "ORCHPHARMA": 20,
  "ORIANA": 20,
  "ORICONENT": 20,
  "ORIENTALTL": 20,
  "ORIENTBELL": 20,
  "ORIENTCEM": 20,
  "ORIENTCER": 20,
  "ORIENTELEC": 20,
  "ORIENTHOT": 20,
  "ORIENTLTD": 20,
  "ORIENTPPR": 20,
  "ORIENTTECH": 20,
  "ORISSAMINE": 20,
  "ORKLAINDIA": 20,
  "OSEINTRUST": 20,
  "OSELDEVICE": 20,
  "OSWALGREEN": 20,
  "OSWALSEEDS": 20,
  "PACEDIGITK": 20,
  "PAISALO": 20,
  "PAKKA": 20,
  "PALASHSECU": 20,
  "PANSARI": 20,
  "PAR": 20,
  "PARADEEP": 20,
  "PARAGMILK": 20,
  "PARAGON": 20,
  "PARAMATRIX": 20,
  "PARIN": 20,
  "PARKHOTELS": 20,
  "PARTH": 20,
  "PARTYCRUS": 20,
  "PASHUPATI": 20,
  "PATELENG": 20,
  "PATELRMART": 20,
  "PAUSHAKLTD": 20,
  "PAVNAIND": 20,
  "PCBL": 20,
  "PCCL": 20,
  "PCJEWELLER": 20,
  "PDMJEPAPER": 20,
  "PDSL": 20,
  "PELATRO": 20,
  "PENIND": 20,
  "PENTAGON": 20,
  "PFIZER": 20,
  "PFOCUS": 20,
  "PFS": 20,
  "PGHH": 20,
  "PGHL": 20,
  "PGIL": 20,
  "PGINVIT": 20,
  "PHANTOMFX": 20,
  "PHARMABEES": 20,
  "PHOGLOBAL": 20,
  "PICCADIL": 20,
  "PIGL": 20,
  "PILANIINVS": 20,
  "PINELABS": 20,
  "PIONEEREMB": 20,
  "PIONRINV": 20,
  "PIRAMALFIN": 20,
  "PITTIENG": 20,
  "PIXTRANS": 20,
  "PKTEA": 20,
  "PLASTIBLEN": 20,
  "PLATIND": 20,
  "PML": 20,
  "PNBGILTS": 20,
  "PNCINFRA": 20,
  "PNGSREVA": 20,
  "POCL": 20,
  "PODDARMENT": 20,
  "POKARNA": 20,
  "POLYMED": 20,
  "POLYPLEX": 20,
  "PONNIERODE": 20,
  "POONAWALLA": 20,
  "POWERMECH": 20,
  "PPLPHARMA": 20,
  "PRABHA": 20,
  "PRAENG": 20,
  "PRAJIND": 20,
  "PRAKASH": 20,
  "PRAKASHSTL": 20,
  "PRANIK": 20,
  "PRATHAM": 20,
  "PRAVEG": 20,
  "PRECAM": 20,
  "PRECWIRE": 20,
  "PREMCO": 20,
  "PREMEXPLN": 20,
  "PREMIERPOL": 20,
  "PREMIUM": 20,
  "PRICOLLTD": 20,
  "PRIMESECU": 20,
  "PRIMO": 20,
  "PRINCEPIPE": 20,
  "PRITIKA": 20,
  "PRIVISCL": 20,
  "PRLIND": 20,
  "PROFX": 20,
  "PROPEQUITY": 20,
  "PROSTARM": 20,
  "PROTEAN": 20,
  "PROV": 20,
  "PROZONER": 20,
  "PRSMJOHNSN": 20,
  "PRUDENT": 20,
  "PSB": 20,
  "PSFL": 20,
  "PSPPROJECT": 20,
  "PSUBANK": 20,
  "PSUBANKADD": 20,
  "PSUBNKBEES": 20,
  "PSUBNKIETF": 20,
  "PTC": 20,
  "PTCIL": 20,
  "PTL": 20,
  "PUNJABCHEM": 20,
  "PURVA": 20,
  "PUSHPA": 20,
  "PVP": 20,
  "PVRINOX": 20,
  "PVSL": 20,
  "PVTBANIETF": 20,
  "PVTBANK": 20,
  "PVTBANKADD": 20,
  "PVTBKGROWW": 20,
  "PWL": 20,
  "PYRAMID": 20,
  "QGOLDHALF": 20,
  "QLINE": 20,
  "QMSMEDI": 20,
  "QNIFTY": 20,
  "QUADFUTURE": 20,
  "QUAL30IETF": 20,
  "QUALITY30": 20,
  "QUESS": 20,
  "QUESTLAB": 20,
  "QUINT": 20,
  "RACLGEAR": 20,
  "RADAAN": 20,
  "RADHIKAJWE": 20,
  "RADIANTCMS": 20,
  "RAILTEL": 20,
  "RAIN": 20,
  "RAINBOW": 20,
  "RAJINDLTD": 20,
  "RAJPALAYAM": 20,
  "RAJPUTANA": 20,
  "RAJRATAN": 20,
  "RAJSREESUG": 20,
  "RALLIS": 20,
  "RAMANEWS": 20,
  "RAMAPHO": 20,
  "RAMBHAJO": 20,
  "RAMCOCEM": 20,
  "RAMCOIND": 20,
  "RAMKY": 20,
  "RAMRAT": 20,
  "RANASUG": 20,
  "RANEHOLDIN": 20,
  "RAPIDFLEET": 20,
  "RAPPID": 20,
  "RATEGAIN": 20,
  "RATNAMANI": 20,
  "RATNAVEER": 20,
  "RAYMOND": 20,
  "RAYMONDLSL": 20,
  "RAYMONDREL": 20,
  "RBA": 20,
  "RBMINFRA": 20,
  "RBZJEWEL": 20,
  "RCDL": 20,
  "RCF": 20,
  "READYMIX": 20,
  "REDINGTON": 20,
  "REDTAPE": 20,
  "REFEX": 20,
  "REGENCERAM": 20,
  "RELAXO": 20,
  "RELCHEMQ": 20,
  "RELIABLE": 20,
  "RELIGARE": 20,
  "RELTD": 20,
  "REMSONSIND": 20,
  "REMUS": 20,
  "RENUKA": 20,
  "REPCOHOME": 20,
  "REPRO": 20,
  "RESPONIND": 20,
  "RETAIL": 20,
  "RGL": 20,
  "RHETAN": 20,
  "RHIM": 20,
  "RHL": 20,
  "RICOAUTO": 20,
  "RIIL": 20,
  "RIIT": 20,
  "RILINFRA": 20,
  "RIR": 20,
  "RISHABH": 20,
  "RITCO": 20,
  "RITES": 20,
  "RKDL": 20,
  "RKFORGE": 20,
  "RKSWAMY": 20,
  "RMC": 20,
  "RML": 20,
  "RNFI": 20,
  "ROADSTAR": 20,
  "ROCKINGDCE": 20,
  "ROCKPP": 20,
  "ROHLTD": 20,
  "ROLEXRINGS": 20,
  "ROML": 20,
  "ROSSARI": 20,
  "ROSSELLIND": 20,
  "ROSSTECH": 20,
  "ROTO": 20,
  "ROUTE": 20,
  "ROYALARC": 20,
  "RPEL": 20,
  "RPGLIFE": 20,
  "RPOWER": 20,
  "RPPINFRA": 20,
  "RPPL": 20,
  "RPTECH": 20,
  "RRIL": 20,
  "RRKABEL": 20,
  "RSDFIN": 20,
  "RSL": 20,
  "RSYSTEMS": 20,
  "RTL": 20,
  "RTNINDIA": 20,
  "RTNPOWER": 20,
  "RUBFILA": 20,
  "RUBICON": 20,
  "RUCHINFRA": 20,
  "RUCHIRA": 20,
  "RULKA": 20,
  "RUPA": 20,
  "RUSHIL": 20,
  "RUSTOMJEE": 20,
  "RVHL": 20,
  "RVTH": 20,
  "SACHEEROME": 20,
  "SADHAV": 20,
  "SAFARI": 20,
  "SAFEENTP": 20,
  "SAGARDEEP": 20,
  "SAGCEM": 20,
  "SAGILITY": 20,
  "SAHAJSOLAR": 20,
  "SAHANA": 20,
  "SAHLIBHFI": 20,
  "SAHYADRI": 20,
  "SAILIFE": 20,
  "SAIPARENT": 20,
  "SAKHTISUG": 20,
  "SALASAR": 20,
  "SALONA": 20,
  "SALZERELEC": 20,
  "SAMBHV": 20,
  "SAMHI": 20,
  "SAMMAANCAP": 20,
  "SAMPANN": 20,
  "SANDESH": 20,
  "SANDHAR": 20,
  "SANDUMA": 20,
  "SANGAMIND": 20,
  "SANGHVIMOV": 20,
  "SANOFI": 20,
  "SANOFICONR": 20,
  "SANSERA": 20,
  "SANSTAR": 20,
  "SAPPHIRE": 20,
  "SAPPL": 20,
  "SARDAEN": 20,
  "SAREGAMA": 20,
  "SARLAPOLY": 20,
  "SATIA": 20,
  "SATIN": 20,
  "SATTVAENGG": 20,
  "SAURASHCEM": 20,
  "SAVY": 20,
  "SAWALIYA": 20,
  "SBC": 20,
  "SBCL": 20,
  "SBFC": 20,
  "SBGLP": 20,
  "SBIBPB": 20,
  "SBIETFCON": 20,
  "SBIETFIT": 20,
  "SBIETFPB": 20,
  "SBIETFQLTY": 20,
  "SBIMIDMOM": 20,
  "SBINEQWETF": 20,
  "SBINMID150": 20,
  "SBISILVER": 20,
  "SBISMLETF": 20,
  "SBIVALETF": 20,
  "SCANSTL": 20,
  "SCHAEFFLER": 20,
  "SCHAND": 20,
  "SCI": 20,
  "SCILAL": 20,
  "SCODATUBES": 20,
  "SCPL": 20,
  "SDBL": 20,
  "SDREAMS": 20,
  "SEAMECLTD": 20,
  "SEDEMAC": 20,
  "SEIL": 20,
  "SEITINVIT": 20,
  "SELECTIPO": 20,
  "SELLOWRAP": 20,
  "SELMC": 20,
  "SENCO": 20,
  "SENORES": 20,
  "SENSEXADD": 20,
  "SENSEXAXIS": 20,
  "SENSEXBETA": 20,
  "SENSEXETF": 20,
  "SENSEXIETF": 20,
  "SEPC": 20,
  "SERVOTECH": 20,
  "SESHAPAPER": 20,
  "SETFGOLD": 20,
  "SETFNIF50": 20,
  "SETFNIFBK": 20,
  "SETFNN50": 20,
  "SFL": 20,
  "SFML": 20,
  "SGFIN": 20,
  "SGIL": 20,
  "SGMART": 20,
  "SHADOWFAX": 20,
  "SHAH": 20,
  "SHAHALLOYS": 20,
  "SHAILY": 20,
  "SHAKTIPUMP": 20,
  "SHALBY": 20,
  "SHALPAINTS": 20,
  "SHANKARA": 20,
  "SHANTHALA": 20,
  "SHANTI": 20,
  "SHANTIGEAR": 20,
  "SHANTIGOLD": 20,
  "SHARDACROP": 20,
  "SHARDAMOTR": 20,
  "SHAREINDIA": 20,
  "SHARIABEES": 20,
  "SHBAJRG": 20,
  "SHEETAL": 20,
  "SHIGAN": 20,
  "SHILCTECH": 20,
  "SHILPAMED": 20,
  "SHINDL": 20,
  "SHIVASHRIT": 20,
  "SHIVATEX": 20,
  "SHK": 20,
  "SHKSIL": 20,
  "SHOPERSTOP": 20,
  "SHRADHA": 20,
  "SHREDIGCEM": 20,
  "SHREEDHAR": 20,
  "SHREEKARNI": 20,
  "SHREEOSFM": 20,
  "SHREEPUSHK": 20,
  "SHREERAMA": 20,
  "SHREMINVIT": 20,
  "SHREYANIND": 20,
  "SHRIKRISH": 20,
  "SHRINGARMS": 20,
  "SHRIPISTON": 20,
  "SHRIRAMPPS": 20,
  "SHRITECH": 20,
  "SHUBHSHREE": 20,
  "SHYAMMETL": 20,
  "SICAGEN": 20,
  "SIDDHICOTS": 20,
  "SIGIND": 20,
  "SIGMA": 20,
  "SIGNATURE": 20,
  "SIGNPOST": 20,
  "SIKA": 20,
  "SIKKO": 20,
  "SIL": 20,
  "SILGO": 20,
  "SILINV": 20,
  "SILLYMONKS": 20,
  "SILVER": 20,
  "SILVER1": 20,
  "SILVER360": 20,
  "SILVERADD": 20,
  "SILVERAG": 20,
  "SILVERAXIS": 20,
  "SILVERBEES": 20,
  "SILVERBETA": 20,
  "SILVERBND": 20,
  "SILVERCASE": 20,
  "SILVERIETF": 20,
  "SIMCA": 20,
  "SIMPLEXINF": 20,
  "SINCLAIR": 20,
  "SINDHUTRAD": 20,
  "SINGERIND": 20,
  "SINTERCOM": 20,
  "SIRCA": 20,
  "SIS": 20,
  "SIYSIL": 20,
  "SJLOGISTIC": 20,
  "SJS": 20,
  "SJVN": 20,
  "SKFINDIA": 20,
  "SKFINDUS": 20,
  "SKIPPER": 20,
  "SKMEGGPROD": 20,
  "SKP": 20,
  "SKYGOLD": 20,
  "SMALL250": 20,
  "SMALLADD": 20,
  "SMALLCAP": 20,
  "SMALLGROWW": 20,
  "SMALLIETF": 20,
  "SMARTWORKS": 20,
  "SMCGLOBAL": 20,
  "SML100CASE": 20,
  "SMLMAH": 20,
  "SMLT": 20,
  "SMSPHARMA": 20,
  "SNOWMAN": 20,
  "SNXT30BEES": 20,
  "SNXT50BETA": 20,
  "SOBHA": 20,
  "SOLARA": 20,
  "SOLARWORLD": 20,
  "SOLEX": 20,
  "SOMANYCERA": 20,
  "SOMICONVEY": 20,
  "SONAMLTD": 20,
  "SONATSOFTW": 20,
  "SOTL": 20,
  "SOUTHBANK": 20,
  "SOUTHWEST": 20,
  "SPAL": 20,
  "SPANDANA": 20,
  "SPCL": 20,
  "SPCON": 20,
  "SPECIALITY": 20,
  "SPECTRUM": 20,
  "SPENCERS": 20,
  "SPIC": 20,
  "SPLIL": 20,
  "SPLPETRO": 20,
  "SPMLINFRA": 20,
  "SPORTKING": 20,
  "SPUNWEB": 20,
  "SRD": 20,
  "SREEL": 20,
  "SRGHFL": 20,
  "SRHHYPOLTD": 20,
  "SRM": 20,
  "SRTL": 20,
  "SSDL": 20,
  "SSEGL": 20,
  "SSFLPP": 20,
  "SSWL": 20,
  "STALLION": 20,
  "STANLEY": 20,
  "STAR": 20,
  "STARCEMENT": 20,
  "STARHEALTH": 20,
  "STARPAPER": 20,
  "STARTECK": 20,
  "STCINDIA": 20,
  "STEELCAS": 20,
  "STEELCITY": 20,
  "STEELXIND": 20,
  "STEL": 20,
  "STOVEKRAFT": 20,
  "STRIDERS": 20,
  "STUDDS": 20,
  "STYLAMIND": 20,
  "STYRENIX": 20,
  "SUBAHOTELS": 20,
  "SUBROS": 20,
  "SUDARCOLOR": 20,
  "SUDARSCHEM": 20,
  "SUKHJITS": 20,
  "SULA": 20,
  "SUMICHEM": 20,
  "SUMMITSEC": 20,
  "SUNCLAY": 20,
  "SUNDARAM": 20,
  "SUNDARMFIN": 20,
  "SUNDRMFAST": 20,
  "SUNDROP": 20,
  "SUNREST": 20,
  "SUNTECK": 20,
  "SUNTV": 20,
  "SUPERHOUSE": 20,
  "SUPRAJIT": 20,
  "SUPREME": 20,
  "SUPREMEINF": 20,
  "SUPRIYA": 20,
  "SURAJEST": 20,
  "SURAJLTD": 20,
  "SURAKSHA": 20,
  "SURANASOL": 20,
  "SURANAT&P": 20,
  "SURYALA": 20,
  "SURYALAXMI": 20,
  "SURYAROSNI": 20,
  "SURYODAY": 20,
  "SUVEN": 20,
  "SUYOG": 20,
  "SWANCORP": 20,
  "SWARAJ": 20,
  "SWARAJENG": 20,
  "SWELECTES": 20,
  "SWSOLAR": 20,
  "SYMPHONY": 20,
  "SYNCOMF": 20,
  "SYNGENE": 20,
  "SYRMA": 20,
  "SYSTANGO": 20,
  "TAALTECH": 20,
  "TAINWALCHM": 20,
  "TAJGVK": 20,
  "TALBROAUTO": 20,
  "TANLA": 20,
  "TARACHAND": 20,
  "TARC": 20,
  "TARIL": 20,
  "TARSONS": 20,
  "TASTYBITE": 20,
  "TATACHEM": 20,
  "TATACOMM": 20,
  "TATAGOLD": 20,
  "TATAINVEST": 20,
  "TATATECH": 20,
  "TATSILV": 20,
  "TATVA": 20,
  "TAURIAN": 20,
  "TBI": 20,
  "TBOTEK": 20,
  "TBZ": 20,
  "TCC": 20,
  "TCI": 20,
  "TCIEXP": 20,
  "TCL": 20,
  "TCPLPACK": 20,
  "TDPOWERSYS": 20,
  "TEAMGTY": 20,
  "TEAMLEASE": 20,
  "TEAMTECH": 20,
  "TECH": 20,
  "TECHNOE": 20,
  "TECHNVISN": 20,
  "TECILCHEM": 20,
  "TEGA": 20,
  "TEJA": 20,
  "TEJASNET": 20,
  "TEMBO": 20,
  "TENNIND": 20,
  "TEXINFRA": 20,
  "TEXMOPIPES": 20,
  "TEXRAIL": 20,
  "TFCILTD": 20,
  "TFL": 20,
  "TGBHOTELS": 20,
  "THEINVEST": 20,
  "THEJO": 20,
  "THEMISMED": 20,
  "THERMAX": 20,
  "THOMASCOOK": 20,
  "THOMASCOTT": 20,
  "THYROCARE": 20,
  "TI": 20,
  "TIIL": 20,
  "TIL": 20,
  "TIMETECHNO": 20,
  "TIMEX": 20,
  "TIMKEN": 20,
  "TINNARUBR": 20,
  "TIPSFILMS": 20,
  "TIPSMUSIC": 20,
  "TIRUMALCHM": 20,
  "TITAGARH": 20,
  "TMB": 20,
  "TMCV": 20,
  "TNIDETF": 20,
  "TNPETRO": 20,
  "TNPL": 20,
  "TNTELE": 20,
  "TOLINS": 20,
  "TOP100CASE": 20,
  "TOP10ADD": 20,
  "TOP15IETF": 20,
  "TOP20": 20,
  "TORNTPOWER": 20,
  "TOTAL": 20,
  "TOUCHWOOD": 20,
  "TPHQ": 20,
  "TPLPLASTEH": 20,
  "TRACXN": 20,
  "TRANSPEK": 20,
  "TRANSRAILL": 20,
  "TRANSTEEL": 20,
  "TREL": 20,
  "TRF": 20,
  "TRIDENT": 20,
  "TRIGYN": 20,
  "TRITURBINE": 20,
  "TRUALT": 20,
  "TRUST": 20,
  "TSC": 20,
  "TSFINV": 20,
  "TTKHLTCARE": 20,
  "TTKPRESTIG": 20,
  "TTML": 20,
  "TUNWAL": 20,
  "TURTLEMINT": 20,
  "TVSELECT": 20,
  "TVSHLTD": 20,
  "TVSINVIT": 20,
  "TVSSRICHAK": 20,
  "TVTODAY": 20,
  "TVVISION": 20,
  "TWCGOLDETF": 20,
  "UBL": 20,
  "UCAL": 20,
  "UCOBANK": 20,
  "UDS": 20,
  "UEL": 20,
  "UFLEX": 20,
  "UFO": 20,
  "UGARSUGAR": 20,
  "UGROCAP": 20,
  "UJJIVANSFB": 20,
  "ULTRAMAR": 20,
  "UMA": 20,
  "UMIYA-MRO": 20,
  "UNIECOM": 20,
  "UNIENTER": 20,
  "UNILEX": 20,
  "UNIONGOLD": 20,
  "UNIPARTS": 20,
  "UNITEDTEA": 20,
  "UNIVCABLES": 20,
  "URBAN": 20,
  "URBANCO": 20,
  "URJA": 20,
  "USHAFIN": 20,
  "USHAMART": 20,
  "UTIAMC": 20,
  "UTKARSHBNK": 20,
  "UTTAMSUGAR": 20,
  "UYFINCORP": 20,
  "V2RETAIL": 20,
  "VADILALIND": 20,
  "VAIBHAVGBL": 20,
  "VAKRANGEE": 20,
  "VAL30IETF": 20,
  "VALUE": 20,
  "VALUE360": 20,
  "VALUEAXIS": 20,
  "VAML": 20,
  "VARDMNPOLY": 20,
  "VARROC": 20,
  "VASWANI": 20,
  "VDEAL": 20,
  "VEDPOWER": 20,
  "VEEDOL": 20,
  "VENKEYS": 20,
  "VENUSPIPES": 20,
  "VERANDA": 20,
  "VERTIS": 20,
  "VESUVIUS": 20,
  "VGINFOTECH": 20,
  "VGL": 20,
  "VGUARD": 20,
  "VHL": 20,
  "VIDHIING": 20,
  "VIESL": 20,
  "VIJAYA": 20,
  "VIJAYPD": 20,
  "VIKRAMSOLR": 20,
  "VIKRAN": 20,
  "VILAS": 20,
  "VIMTALABS": 20,
  "VINATIORGA": 20,
  "VINCOFE": 20,
  "VINDHYATEL": 20,
  "VINNY": 20,
  "VINYAS": 20,
  "VINYLINDIA": 20,
  "VIPIND": 20,
  "VISAKAIND": 20,
  "VISHNU": 20,
  "VISHNUINFR": 20,
  "VIYASH": 20,
  "VLSFINANCE": 20,
  "VMARCIND": 20,
  "VMART": 20,
  "VOEPL": 20,
  "VOGL": 20,
  "VOLERCAR": 20,
  "VOLTAMP": 20,
  "VRAJ": 20,
  "VRLLOG": 20,
  "VSSL": 20,
  "VSTIND": 20,
  "VSTL": 20,
  "VSTTILLERS": 20,
  "VTL": 20,
  "WAAREERTL": 20,
  "WABAG": 20,
  "WAKEFIT": 20,
  "WALCHANNAG": 20,
  "WANBURY": 20,
  "WCIL": 20,
  "WEALTH": 20,
  "WEIZMANIND": 20,
  "WELCORP": 20,
  "WELENT": 20,
  "WELSPUNLIV": 20,
  "WENDT": 20,
  "WESTLIFE": 20,
  "WEWORK": 20,
  "WHEELS": 20,
  "WHIRLPOOL": 20,
  "WILLAMAGOR": 20,
  "WINDLAS": 20,
  "WINDMACHIN": 20,
  "WINSOL": 20,
  "WIPL": 20,
  "WOCKPHARMA": 20,
  "WOMANCART": 20,
  "WONDERLA": 20,
  "WORTHPERI": 20,
  "WPIL": 20,
  "WSI": 20,
  "WSTCSTPAPR": 20,
  "XCHANGING": 20,
  "XELPMOC": 20,
  "XPROINDIA": 20,
  "XTGLOBAL": 20,
  "YASHO": 20,
  "YASHOPTICS": 20,
  "YATHARTH": 20,
  "YATRA": 20,
  "YCCL": 20,
  "YUKEN": 20,
  "ZAGGLE": 20,
  "ZEAL": 20,
  "ZEEL": 20,
  "ZENITHDRUG": 20,
  "ZENSARTECH": 20,
  "ZENTEC": 20,
  "ZFCVINDIA": 20,
  "ZFSTEERING": 20,
  "ZODIACLOTH": 20,
  "ZOTA": 20,
  "ZTECH": 20,
  "ZUARI": 20,
  "ZUARIIND": 20,
  "ZYDUSWELL": 20,
  "360ONE": "NB",
  "ABB": "NB",
  "ABCAPITAL": "NB",
  "ADANIENSOL": "NB",
  "ADANIENT": "NB",
  "ADANIGREEN": "NB",
  "ADANIPORTS": "NB",
  "ADANIPOWER": "NB",
  "ALKEM": "NB",
  "AMBER": "NB",
  "AMBUJACEM": "NB",
  "ANGELONE": "NB",
  "APLAPOLLO": "NB",
  "APOLLOHOSP": "NB",
  "ASHOKLEY": "NB",
  "ASIANPAINT": "NB",
  "ASTRAL": "NB",
  "AUBANK": "NB",
  "AUROPHARMA": "NB",
  "AXISBANK": "NB",
  "BAJAJ-AUTO": "NB",
  "BAJAJFINSV": "NB",
  "BAJAJHLDNG": "NB",
  "BAJFINANCE": "NB",
  "BANDHANBNK": "NB",
  "BANKBARODA": "NB",
  "BANKINDIA": "NB",
  "BDL": "NB",
  "BEL": "NB",
  "BHARATFORG": "NB",
  "BHARTIARTL": "NB",
  "BHEL": "NB",
  "BIOCON": "NB",
  "BLUESTARCO": "NB",
  "BOSCHLTD": "NB",
  "BPCL": "NB",
  "BRITANNIA": "NB",
  "BSE": "NB",
  "CAMS": "NB",
  "CANBK": "NB",
  "CDSL": "NB",
  "CGPOWER": "NB",
  "CHOLAFIN": "NB",
  "CIPLA": "NB",
  "COALINDIA": "NB",
  "COCHINSHIP": "NB",
  "COFORGE": "NB",
  "COLPAL": "NB",
  "CONCOR": "NB",
  "CROMPTON": "NB",
  "CUMMINSIND": "NB",
  "DABUR": "NB",
  "DALBHARAT": "NB",
  "DELHIVERY": "NB",
  "DIVISLAB": "NB",
  "DIXON": "NB",
  "DLF": "NB",
  "DMART": "NB",
  "DRREDDY": "NB",
  "EICHERMOT": "NB",
  "ETERNAL": "NB",
  "EXIDEIND": "NB",
  "FEDERALBNK": "NB",
  "FORCEMOT": "NB",
  "FORTIS": "NB",
  "GAIL": "NB",
  "GLENMARK": "NB",
  "GMRAIRPORT": "NB",
  "GODFRYPHLP": "NB",
  "GODREJCP": "NB",
  "GODREJPROP": "NB",
  "GRASIM": "NB",
  "GVT&D": "NB",
  "HAL": "NB",
  "HAVELLS": "NB",
  "HCLTECH": "NB",
  "HDFCAMC": "NB",
  "HDFCBANK": "NB",
  "HDFCLIFE": "NB",
  "HEROMOTOCO": "NB",
  "HINDALCO": "NB",
  "HINDPETRO": "NB",
  "HINDUNILVR": "NB",
  "HINDZINC": "NB",
  "HYUNDAI": "NB",
  "ICICIBANK": "NB",
  "ICICIGI": "NB",
  "ICICIPRULI": "NB",
  "IDEA": "NB",
  "IDFCFIRSTB": "NB",
  "IEX": "NB",
  "INDHOTEL": "NB",
  "INDIANB": "NB",
  "INDIGO": "NB",
  "INDUSINDBK": "NB",
  "INDUSTOWER": "NB",
  "INFY": "NB",
  "INOXWIND": "NB",
  "IOC": "NB",
  "IREDA": "NB",
  "IRFC": "NB",
  "ITC": "NB",
  "JINDALSTEL": "NB",
  "JIOFIN": "NB",
  "JSWENERGY": "NB",
  "JSWSTEEL": "NB",
  "JUBLFOOD": "NB",
  "KALYANKJIL": "NB",
  "KAYNES": "NB",
  "KEI": "NB",
  "KFINTECH": "NB",
  "KOTAKBANK": "NB",
  "KPITTECH": "NB",
  "LAURUSLABS": "NB",
  "LICHSGFIN": "NB",
  "LICI": "NB",
  "LODHA": "NB",
  "LT": "NB",
  "LTF": "NB",
  "LTM": "NB",
  "LUPIN": "NB",
  "M&M": "NB",
  "MANAPPURAM": "NB",
  "MANKIND": "NB",
  "MARICO": "NB",
  "MARUTI": "NB",
  "MAXHEALTH": "NB",
  "MAZDOCK": "NB",
  "MCX": "NB",
  "MFSL": "NB",
  "MOTHERSON": "NB",
  "MOTILALOFS": "NB",
  "MPHASIS": "NB",
  "MUTHOOTFIN": "NB",
  "NAM-INDIA": "NB",
  "NATIONALUM": "NB",
  "NAUKRI": "NB",
  "NBCC": "NB",
  "NESTLEIND": "NB",
  "NHPC": "NB",
  "NMDC": "NB",
  "NTPC": "NB",
  "NUVAMA": "NB",
  "NYKAA": "NB",
  "OBEROIRLTY": "NB",
  "OFSS": "NB",
  "OIL": "NB",
  "ONGC": "NB",
  "PAGEIND": "NB",
  "PATANJALI": "NB",
  "PAYTM": "NB",
  "PERSISTENT": "NB",
  "PETRONET": "NB",
  "PFC": "NB",
  "PGEL": "NB",
  "PHOENIXLTD": "NB",
  "PIDILITIND": "NB",
  "PIIND": "NB",
  "PNB": "NB",
  "PNBHOUSING": "NB",
  "POLICYBZR": "NB",
  "POLYCAB": "NB",
  "POWERGRID": "NB",
  "POWERINDIA": "NB",
  "PREMIERENE": "NB",
  "PRESTIGE": "NB",
  "RADICO": "NB",
  "RBLBANK": "NB",
  "RECLTD": "NB",
  "RELIANCE": "NB",
  "RVNL": "NB",
  "SAIL": "NB",
  "SBICARD": "NB",
  "SBILIFE": "NB",
  "SBIN": "NB",
  "SHREECEM": "NB",
  "SHRIRAMFIN": "NB",
  "SIEMENS": "NB",
  "SOLARINDS": "NB",
  "SONACOMS": "NB",
  "SRF": "NB",
  "SUNPHARMA": "NB",
  "SUPREMEIND": "NB",
  "SUZLON": "NB",
  "SWIGGY": "NB",
  "TATACONSUM": "NB",
  "TATAELXSI": "NB",
  "TATAPOWER": "NB",
  "TATASTEEL": "NB",
  "TCS": "NB",
  "TECHM": "NB",
  "TIINDIA": "NB",
  "TITAN": "NB",
  "TMPV": "NB",
  "TORNTPHARM": "NB",
  "TRENT": "NB",
  "TVSMOTOR": "NB",
  "ULTRACEMCO": "NB",
  "UNIONBANK": "NB",
  "UNITDSPR": "NB",
  "UNOMINDA": "NB",
  "UPL": "NB",
  "VBL": "NB",
  "VEDL": "NB",
  "VMM": "NB",
  "VOLTAS": "NB",
  "WAAREEENER": "NB",
  "WIPRO": "NB",
  "YESBANK": "NB",
  "ZYDUSLIFE": "NB"
 }
}